{
  "slug": "springfield",
  "domain": "springfieldcollegepride.com",
  "scrapedAt": "2026-04-08T02:12:15.003Z",
  "year": 2026,
  "hitting": {
    "players": [
      {
        "name": "DeRosa, Amelia",
        "jerseyNumber": 16,
        "avg": 0.446,
        "ops": 1.089,
        "gp": 19,
        "gs": 19,
        "ab": 65,
        "r": 13,
        "h": 29,
        "doubles": 6,
        "triples": 1,
        "hr": 0,
        "rbi": 20,
        "tb": 37,
        "slg": 0.569,
        "bb": 10,
        "hbp": 0,
        "so": 7,
        "gdp": 0,
        "obp": 0.52,
        "sf": 0,
        "sh": 0,
        "sb": 3,
        "sbAtt": 3
      },
      {
        "name": "Hunter, Reilly",
        "jerseyNumber": 11,
        "avg": 0.367,
        "ops": 0.952,
        "gp": 19,
        "gs": 19,
        "ab": 60,
        "r": 17,
        "h": 22,
        "doubles": 7,
        "triples": 1,
        "hr": 0,
        "rbi": 7,
        "tb": 31,
        "slg": 0.517,
        "bb": 8,
        "hbp": 0,
        "so": 10,
        "gdp": 0,
        "obp": 0.435,
        "sf": 1,
        "sh": 0,
        "sb": 3,
        "sbAtt": 3
      },
      {
        "name": "Katsetos, Kate",
        "jerseyNumber": 2,
        "avg": 0.349,
        "ops": 0.798,
        "gp": 19,
        "gs": 19,
        "ab": 63,
        "r": 8,
        "h": 22,
        "doubles": 3,
        "triples": 1,
        "hr": 0,
        "rbi": 15,
        "tb": 27,
        "slg": 0.429,
        "bb": 2,
        "hbp": 0,
        "so": 3,
        "gdp": 0,
        "obp": 0.369,
        "sf": 0,
        "sh": 0,
        "sb": 1,
        "sbAtt": 1
      },
      {
        "name": "Pecchia, Carissa",
        "jerseyNumber": 27,
        "avg": 0.311,
        "ops": 1.003,
        "gp": 18,
        "gs": 17,
        "ab": 45,
        "r": 6,
        "h": 14,
        "doubles": 3,
        "triples": 0,
        "hr": 2,
        "rbi": 15,
        "tb": 23,
        "slg": 0.511,
        "bb": 16,
        "hbp": 1,
        "so": 8,
        "gdp": 1,
        "obp": 0.492,
        "sf": 1,
        "sh": 0,
        "sb": 0,
        "sbAtt": 0
      },
      {
        "name": "Ball, Haley",
        "jerseyNumber": 1,
        "avg": 0.304,
        "ops": 0.818,
        "gp": 19,
        "gs": 19,
        "ab": 46,
        "r": 9,
        "h": 14,
        "doubles": 1,
        "triples": 0,
        "hr": 0,
        "rbi": 4,
        "tb": 15,
        "slg": 0.326,
        "bb": 15,
        "hbp": 2,
        "so": 7,
        "gdp": 0,
        "obp": 0.492,
        "sf": 0,
        "sh": 0,
        "sb": 5,
        "sbAtt": 5
      },
      {
        "name": "Falotico, Taylor",
        "jerseyNumber": 6,
        "avg": 0.277,
        "ops": 0.623,
        "gp": 18,
        "gs": 18,
        "ab": 47,
        "r": 12,
        "h": 13,
        "doubles": 0,
        "triples": 0,
        "hr": 0,
        "rbi": 4,
        "tb": 13,
        "slg": 0.277,
        "bb": 5,
        "hbp": 0,
        "so": 7,
        "gdp": 0,
        "obp": 0.346,
        "sf": 0,
        "sh": 0,
        "sb": 3,
        "sbAtt": 4
      },
      {
        "name": "Testo, Madi",
        "jerseyNumber": 25,
        "avg": 0.389,
        "ops": 0.833,
        "gp": 8,
        "gs": 3,
        "ab": 18,
        "r": 2,
        "h": 7,
        "doubles": 1,
        "triples": 0,
        "hr": 0,
        "rbi": 2,
        "tb": 8,
        "slg": 0.444,
        "bb": 0,
        "hbp": 0,
        "so": 2,
        "gdp": 0,
        "obp": 0.389,
        "sf": 0,
        "sh": 0,
        "sb": 0,
        "sbAtt": 0
      },
      {
        "name": "King, Madison",
        "jerseyNumber": 18,
        "avg": 0.333,
        "ops": 0.802,
        "gp": 12,
        "gs": 9,
        "ab": 24,
        "r": 4,
        "h": 8,
        "doubles": 2,
        "triples": 0,
        "hr": 0,
        "rbi": 4,
        "tb": 10,
        "slg": 0.417,
        "bb": 2,
        "hbp": 0,
        "so": 10,
        "gdp": 0,
        "obp": 0.385,
        "sf": 0,
        "sh": 0,
        "sb": 1,
        "sbAtt": 1
      },
      {
        "name": "Vlahakis, Christina",
        "jerseyNumber": 21,
        "avg": 0.333,
        "ops": 0.666,
        "gp": 3,
        "gs": 0,
        "ab": 3,
        "r": 0,
        "h": 1,
        "doubles": 0,
        "triples": 0,
        "hr": 0,
        "rbi": 0,
        "tb": 1,
        "slg": 0.333,
        "bb": 0,
        "hbp": 0,
        "so": 1,
        "gdp": 0,
        "obp": 0.333,
        "sf": 0,
        "sh": 0,
        "sb": 0,
        "sbAtt": 0
      },
      {
        "name": "Powers, Rachel",
        "jerseyNumber": 7,
        "avg": 0.292,
        "ops": 0.679,
        "gp": 9,
        "gs": 8,
        "ab": 24,
        "r": 5,
        "h": 7,
        "doubles": 1,
        "triples": 0,
        "hr": 0,
        "rbi": 0,
        "tb": 8,
        "slg": 0.333,
        "bb": 2,
        "hbp": 0,
        "so": 4,
        "gdp": 0,
        "obp": 0.346,
        "sf": 0,
        "sh": 0,
        "sb": 3,
        "sbAtt": 3
      },
      {
        "name": "Spingola, Tessa",
        "jerseyNumber": 13,
        "avg": 0.25,
        "ops": 0.65,
        "gp": 5,
        "gs": 0,
        "ab": 4,
        "r": 0,
        "h": 1,
        "doubles": 0,
        "triples": 0,
        "hr": 0,
        "rbi": 0,
        "tb": 1,
        "slg": 0.25,
        "bb": 0,
        "hbp": 1,
        "so": 2,
        "gdp": 0,
        "obp": 0.4,
        "sf": 0,
        "sh": 0,
        "sb": 0,
        "sbAtt": 0
      },
      {
        "name": "Santiago, Emilia",
        "jerseyNumber": 19,
        "avg": 0.242,
        "ops": 0.615,
        "gp": 14,
        "gs": 12,
        "ab": 33,
        "r": 1,
        "h": 8,
        "doubles": 1,
        "triples": 0,
        "hr": 0,
        "rbi": 6,
        "tb": 9,
        "slg": 0.273,
        "bb": 5,
        "hbp": 0,
        "so": 2,
        "gdp": 0,
        "obp": 0.342,
        "sf": 0,
        "sh": 2,
        "sb": 1,
        "sbAtt": 1
      },
      {
        "name": "Levesque, Aurora",
        "jerseyNumber": 23,
        "avg": 0.214,
        "ops": 0.67,
        "gp": 6,
        "gs": 6,
        "ab": 14,
        "r": 1,
        "h": 3,
        "doubles": 2,
        "triples": 0,
        "hr": 0,
        "rbi": 2,
        "tb": 5,
        "slg": 0.357,
        "bb": 2,
        "hbp": 0,
        "so": 4,
        "gdp": 0,
        "obp": 0.313,
        "sf": 0,
        "sh": 1,
        "sb": 0,
        "sbAtt": 0
      },
      {
        "name": "Eckles , Brynlee",
        "jerseyNumber": 8,
        "avg": 0.176,
        "ops": 0.469,
        "gp": 12,
        "gs": 12,
        "ab": 34,
        "r": 3,
        "h": 6,
        "doubles": 1,
        "triples": 0,
        "hr": 0,
        "rbi": 1,
        "tb": 7,
        "slg": 0.206,
        "bb": 4,
        "hbp": 0,
        "so": 7,
        "gdp": 0,
        "obp": 0.263,
        "sf": 0,
        "sh": 3,
        "sb": 0,
        "sbAtt": 0
      },
      {
        "name": "Swords, Sammy",
        "jerseyNumber": 22,
        "avg": 0.176,
        "ops": 0.498,
        "gp": 10,
        "gs": 6,
        "ab": 17,
        "r": 3,
        "h": 3,
        "doubles": 1,
        "triples": 0,
        "hr": 0,
        "rbi": 1,
        "tb": 4,
        "slg": 0.235,
        "bb": 2,
        "hbp": 0,
        "so": 5,
        "gdp": 0,
        "obp": 0.263,
        "sf": 0,
        "sh": 0,
        "sb": 0,
        "sbAtt": 0
      },
      {
        "name": "Bohlander, Addy",
        "jerseyNumber": 9,
        "avg": 0,
        "ops": 0.125,
        "gp": 7,
        "gs": 3,
        "ab": 7,
        "r": 2,
        "h": 0,
        "doubles": 0,
        "triples": 0,
        "hr": 0,
        "rbi": 0,
        "tb": 0,
        "slg": 0,
        "bb": 1,
        "hbp": 0,
        "so": 2,
        "gdp": 0,
        "obp": 0.125,
        "sf": 0,
        "sh": 0,
        "sb": 0,
        "sbAtt": 0
      },
      {
        "name": "Tse, Maddie",
        "jerseyNumber": 14,
        "avg": 0,
        "ops": 0.375,
        "gp": 8,
        "gs": 1,
        "ab": 5,
        "r": 3,
        "h": 0,
        "doubles": 0,
        "triples": 0,
        "hr": 0,
        "rbi": 0,
        "tb": 0,
        "slg": 0,
        "bb": 3,
        "hbp": 0,
        "so": 2,
        "gdp": 0,
        "obp": 0.375,
        "sf": 0,
        "sh": 0,
        "sb": 1,
        "sbAtt": 1
      },
      {
        "name": "Hammer, Ariana",
        "jerseyNumber": 20,
        "avg": 0,
        "ops": 0,
        "gp": 5,
        "gs": 0,
        "ab": 0,
        "r": 1,
        "h": 0,
        "doubles": 0,
        "triples": 0,
        "hr": 0,
        "rbi": 0,
        "tb": 0,
        "slg": 0,
        "bb": 0,
        "hbp": 0,
        "so": 0,
        "gdp": 0,
        "obp": 0,
        "sf": 0,
        "sh": 0,
        "sb": 0,
        "sbAtt": 0
      }
    ],
    "totals": {
      "avg": 0.31,
      "ops": 0.795,
      "gp": 19,
      "gs": 19,
      "ab": 509,
      "r": 90,
      "h": 158,
      "doubles": 29,
      "triples": 3,
      "hr": 2,
      "rbi": 81,
      "tb": 199,
      "slg": 0.391,
      "bb": 77,
      "hbp": 4,
      "so": 83,
      "gdp": 1,
      "obp": 0.404,
      "sf": 2,
      "sh": 6,
      "sb": 21,
      "sbAtt": 22
    },
    "opponents": {
      "avg": 0.285,
      "ops": 0.708,
      "gp": 19,
      "gs": 19,
      "ab": 512,
      "r": 79,
      "h": 146,
      "doubles": 25,
      "triples": 7,
      "hr": 3,
      "rbi": 69,
      "tb": 194,
      "slg": 0.379,
      "bb": 34,
      "hbp": 2,
      "so": 91,
      "gdp": 1,
      "obp": 0.329,
      "sf": 5,
      "sh": 7,
      "sb": 23,
      "sbAtt": 30
    }
  },
  "pitching": {
    "players": [
      {
        "name": "DeRosa, Amelia",
        "jerseyNumber": 16,
        "era": 1.96,
        "whip": 1.2,
        "w": 9,
        "l": 3,
        "app": 12,
        "gs": 3,
        "cg": 2,
        "sho": 0,
        "sv": 0,
        "ip": 75,
        "h": 70,
        "r": 27,
        "er": 21,
        "bb": 20,
        "so": 63,
        "doubles": 15,
        "triples": 1,
        "hr": 2,
        "ab": 285,
        "bAvg": 0.246,
        "wp": 3,
        "hbp": 0,
        "bk": 0,
        "sfa": 2,
        "sha": 4
      },
      {
        "name": "Rimshnick, Julia",
        "jerseyNumber": 3,
        "era": 5.88,
        "whip": 1.8,
        "w": 5,
        "l": 2,
        "app": 17,
        "gs": 16,
        "cg": 7,
        "sho": 0,
        "sv": 1,
        "ip": 50,
        "h": 76,
        "r": 52,
        "er": 42,
        "bb": 14,
        "so": 28,
        "doubles": 10,
        "triples": 6,
        "hr": 1,
        "ab": 227,
        "bAvg": 0.335,
        "wp": 4,
        "hbp": 2,
        "bk": 0,
        "sfa": 3,
        "sha": 3
      }
    ],
    "totals": {
      "era": 3.47,
      "whip": 1.44,
      "w": 14,
      "l": 5,
      "app": 29,
      "gs": 19,
      "cg": 9,
      "sho": 0,
      "sv": 1,
      "ip": 125,
      "h": 146,
      "r": 79,
      "er": 62,
      "bb": 34,
      "so": 391,
      "doubles": 25,
      "triples": 7,
      "hr": 3,
      "ab": 512,
      "bAvg": 0.285,
      "wp": 7,
      "hbp": 2,
      "bk": 0,
      "sfa": 5,
      "sha": 7
    },
    "opponents": {
      "era": 4.31,
      "whip": 1.99,
      "w": 5,
      "l": 14,
      "app": 32,
      "gs": 19,
      "cg": 11,
      "sho": 0,
      "sv": 0,
      "ip": 118.2,
      "h": 158,
      "r": 90,
      "er": 73,
      "bb": 77,
      "so": 383,
      "doubles": 29,
      "triples": 3,
      "hr": 2,
      "ab": 509,
      "bAvg": 0.31,
      "wp": 13,
      "hbp": 4,
      "bk": 0,
      "sfa": 2,
      "sha": 6
    }
  },
  "fielding": {
    "players": [
      {
        "name": "Pecchia, Carissa",
        "jerseyNumber": 27,
        "tc": 70,
        "po": 60,
        "a": 10,
        "e": 0,
        "fldPct": 1,
        "dp": 1,
        "sba": 11,
        "csb": 6,
        "pb": 0,
        "ci": 0
      },
      {
        "name": "Falotico, Taylor",
        "jerseyNumber": 6,
        "tc": 34,
        "po": 33,
        "a": 1,
        "e": 0,
        "fldPct": 1,
        "dp": 1,
        "sba": 0,
        "csb": 0,
        "pb": 0,
        "ci": 0
      },
      {
        "name": "Levesque, Aurora",
        "jerseyNumber": 23,
        "tc": 19,
        "po": 17,
        "a": 2,
        "e": 0,
        "fldPct": 1,
        "dp": 0,
        "sba": 9,
        "csb": 1,
        "pb": 0,
        "ci": 0
      },
      {
        "name": "Testo, Madi",
        "jerseyNumber": 25,
        "tc": 15,
        "po": 14,
        "a": 1,
        "e": 0,
        "fldPct": 1,
        "dp": 0,
        "sba": 3,
        "csb": 0,
        "pb": 0,
        "ci": 0
      },
      {
        "name": "Rimshnick, Julia",
        "jerseyNumber": 3,
        "tc": 11,
        "po": 2,
        "a": 9,
        "e": 0,
        "fldPct": 1,
        "dp": 0,
        "sba": 11,
        "csb": 1,
        "pb": 0,
        "ci": 0
      },
      {
        "name": "Swords, Sammy",
        "jerseyNumber": 22,
        "tc": 10,
        "po": 10,
        "a": 0,
        "e": 0,
        "fldPct": 1,
        "dp": 0,
        "sba": 0,
        "csb": 0,
        "pb": 0,
        "ci": 0
      },
      {
        "name": "King, Madison",
        "jerseyNumber": 18,
        "tc": 6,
        "po": 5,
        "a": 1,
        "e": 0,
        "fldPct": 1,
        "dp": 0,
        "sba": 0,
        "csb": 0,
        "pb": 0,
        "ci": 0
      },
      {
        "name": "Tse, Maddie",
        "jerseyNumber": 14,
        "tc": 4,
        "po": 4,
        "a": 0,
        "e": 0,
        "fldPct": 1,
        "dp": 0,
        "sba": 0,
        "csb": 0,
        "pb": 0,
        "ci": 0
      },
      {
        "name": "Katsetos, Kate",
        "jerseyNumber": 2,
        "tc": 116,
        "po": 111,
        "a": 3,
        "e": 2,
        "fldPct": 0.983,
        "dp": 1,
        "sba": 0,
        "csb": 0,
        "pb": 0,
        "ci": 0
      },
      {
        "name": "Powers, Rachel",
        "jerseyNumber": 7,
        "tc": 27,
        "po": 16,
        "a": 10,
        "e": 1,
        "fldPct": 0.963,
        "dp": 0,
        "sba": 0,
        "csb": 0,
        "pb": 0,
        "ci": 0
      },
      {
        "name": "DeRosa, Amelia",
        "jerseyNumber": 16,
        "tc": 51,
        "po": 9,
        "a": 40,
        "e": 2,
        "fldPct": 0.961,
        "dp": 0,
        "sba": 12,
        "csb": 6,
        "pb": 0,
        "ci": 0
      },
      {
        "name": "Eckles , Brynlee",
        "jerseyNumber": 8,
        "tc": 34,
        "po": 19,
        "a": 13,
        "e": 2,
        "fldPct": 0.941,
        "dp": 1,
        "sba": 0,
        "csb": 0,
        "pb": 0,
        "ci": 0
      },
      {
        "name": "Ball, Haley",
        "jerseyNumber": 1,
        "tc": 32,
        "po": 29,
        "a": 1,
        "e": 2,
        "fldPct": 0.938,
        "dp": 0,
        "sba": 0,
        "csb": 0,
        "pb": 0,
        "ci": 0
      },
      {
        "name": "Santiago, Emilia",
        "jerseyNumber": 19,
        "tc": 35,
        "po": 13,
        "a": 19,
        "e": 3,
        "fldPct": 0.914,
        "dp": 1,
        "sba": 0,
        "csb": 0,
        "pb": 0,
        "ci": 0
      },
      {
        "name": "Hunter, Reilly",
        "jerseyNumber": 11,
        "tc": 70,
        "po": 31,
        "a": 32,
        "e": 7,
        "fldPct": 0.9,
        "dp": 1,
        "sba": 0,
        "csb": 0,
        "pb": 0,
        "ci": 0
      },
      {
        "name": "Bohlander, Addy",
        "jerseyNumber": 9,
        "tc": 4,
        "po": 2,
        "a": 1,
        "e": 1,
        "fldPct": 0.75,
        "dp": 0,
        "sba": 0,
        "csb": 0,
        "pb": 0,
        "ci": 0
      },
      {
        "name": "Spingola, Tessa",
        "jerseyNumber": 13,
        "tc": 0,
        "po": 0,
        "a": 0,
        "e": 0,
        "fldPct": 0,
        "dp": 0,
        "sba": 0,
        "csb": 0,
        "pb": 0,
        "ci": 0
      },
      {
        "name": "Hammer, Ariana",
        "jerseyNumber": 20,
        "tc": 0,
        "po": 0,
        "a": 0,
        "e": 0,
        "fldPct": 0,
        "dp": 0,
        "sba": 0,
        "csb": 0,
        "pb": 0,
        "ci": 0
      },
      {
        "name": "Vlahakis, Christina",
        "jerseyNumber": 21,
        "tc": 0,
        "po": 0,
        "a": 0,
        "e": 0,
        "fldPct": 0,
        "dp": 0,
        "sba": 0,
        "csb": 0,
        "pb": 0,
        "ci": 0
      }
    ],
    "totals": {
      "tc": 538,
      "po": 375,
      "a": 143,
      "e": 20,
      "fldPct": 0.963,
      "dp": 3,
      "sba": 46,
      "csb": 14,
      "pb": 0,
      "ci": 0
    },
    "opponents": {
      "tc": 538,
      "po": 356,
      "a": 161,
      "e": 21,
      "fldPct": 0.961,
      "dp": 4,
      "sba": 42,
      "csb": 2,
      "pb": 4,
      "ci": 0
    }
  }
}