{
  "slug": "wheaton",
  "domain": "wheatoncollegelyons.com",
  "scrapedAt": "2026-04-29T02:42:31.640Z",
  "year": 2026,
  "teamGames": 31,
  "players": [
    {
      "name": "Ashlyn Burt",
      "jerseyNumber": 6,
      "classYear": "Senior",
      "position": "DP",
      "bats": "R",
      "season": {
        "year": 2026,
        "name": "Burt, Ashlyn",
        "avg": 1,
        "ops": 2,
        "gp": 1,
        "gs": 0,
        "ab": 1,
        "r": 0,
        "h": 1,
        "doubles": 0,
        "triples": 0,
        "hr": 0,
        "rbi": 0,
        "tb": 1,
        "slg": 1,
        "bb": 0,
        "hbp": 0,
        "so": 0,
        "gdp": 0,
        "obp": 1,
        "sf": 0,
        "sh": 0,
        "sb": 0,
        "sbAtt": 0,
        "woba": 0.9,
        "pa": 1
      }
    },
    {
      "name": "Ella Molinari",
      "jerseyNumber": 15,
      "classYear": "Junior",
      "position": "IF",
      "bats": "R",
      "season": {
        "year": 2026,
        "name": "Molinari, Ella",
        "avg": 0.418,
        "ops": 1.206,
        "gp": 31,
        "gs": 31,
        "ab": 98,
        "r": 27,
        "h": 41,
        "doubles": 10,
        "triples": 1,
        "hr": 6,
        "rbi": 27,
        "tb": 71,
        "slg": 0.724,
        "bb": 11,
        "hbp": 2,
        "so": 7,
        "gdp": 0,
        "obp": 0.482,
        "sf": 1,
        "sh": 0,
        "sb": 4,
        "sbAtt": 4,
        "woba": 0.507,
        "pa": 112
      }
    },
    {
      "name": "Sam Puma",
      "jerseyNumber": 21,
      "classYear": "Junior",
      "position": "1B",
      "bats": "L",
      "season": {
        "year": 2026,
        "name": "Puma, Sam",
        "avg": 0.5,
        "ops": 1,
        "gp": 2,
        "gs": 0,
        "ab": 2,
        "r": 1,
        "h": 1,
        "doubles": 0,
        "triples": 0,
        "hr": 0,
        "rbi": 0,
        "tb": 1,
        "slg": 0.5,
        "bb": 0,
        "hbp": 0,
        "so": 0,
        "gdp": 0,
        "obp": 0.5,
        "sf": 0,
        "sh": 0,
        "sb": 0,
        "sbAtt": 0,
        "woba": 0.45,
        "pa": 2
      }
    },
    {
      "name": "Peyton Blankenheim-Brown",
      "jerseyNumber": 17,
      "classYear": "Senior",
      "position": "RHP/1B",
      "bats": "R",
      "season": {
        "year": 2026,
        "name": "Blankenheim-Brown, Peyton",
        "avg": 0.315,
        "ops": 0.908,
        "gp": 31,
        "gs": 31,
        "ab": 89,
        "r": 12,
        "h": 28,
        "doubles": 4,
        "triples": 1,
        "hr": 5,
        "rbi": 22,
        "tb": 49,
        "slg": 0.551,
        "bb": 5,
        "hbp": 2,
        "so": 15,
        "gdp": 0,
        "obp": 0.357,
        "sf": 2,
        "sh": 2,
        "sb": 0,
        "sbAtt": 0,
        "woba": 0.387,
        "pa": 100
      }
    },
    {
      "name": "Emma  Boucher",
      "jerseyNumber": 20,
      "classYear": "Junior",
      "position": "3B/C",
      "bats": "R",
      "season": {
        "year": 2026,
        "name": "Boucher, Emma",
        "avg": 0.299,
        "ops": 0.723,
        "gp": 31,
        "gs": 31,
        "ab": 87,
        "r": 14,
        "h": 26,
        "doubles": 4,
        "triples": 0,
        "hr": 0,
        "rbi": 8,
        "tb": 30,
        "slg": 0.345,
        "bb": 9,
        "hbp": 2,
        "so": 7,
        "gdp": 0,
        "obp": 0.378,
        "sf": 0,
        "sh": 4,
        "sb": 1,
        "sbAtt": 2,
        "woba": 0.295,
        "pa": 102
      }
    },
    {
      "name": "Taylor Barry",
      "jerseyNumber": 2,
      "classYear": "Junior",
      "position": "IF",
      "bats": "R",
      "season": {
        "year": 2026,
        "name": "Barry, Taylor",
        "avg": 0.288,
        "ops": 0.723,
        "gp": 25,
        "gs": 23,
        "ab": 73,
        "r": 11,
        "h": 21,
        "doubles": 4,
        "triples": 0,
        "hr": 0,
        "rbi": 5,
        "tb": 25,
        "slg": 0.342,
        "bb": 11,
        "hbp": 0,
        "so": 16,
        "gdp": 0,
        "obp": 0.381,
        "sf": 0,
        "sh": 5,
        "sb": 6,
        "sbAtt": 7,
        "woba": 0.288,
        "pa": 89
      }
    },
    {
      "name": "Mady Bryan",
      "jerseyNumber": 22,
      "classYear": "First Year",
      "position": "1B",
      "bats": "R",
      "season": {
        "year": 2026,
        "name": "Bryan, Mady",
        "avg": 0.268,
        "ops": 0.68,
        "gp": 20,
        "gs": 18,
        "ab": 56,
        "r": 8,
        "h": 15,
        "doubles": 3,
        "triples": 0,
        "hr": 0,
        "rbi": 5,
        "tb": 18,
        "slg": 0.321,
        "bb": 8,
        "hbp": 0,
        "so": 7,
        "gdp": 0,
        "obp": 0.359,
        "sf": 0,
        "sh": 0,
        "sb": 0,
        "sbAtt": 0,
        "woba": 0.288,
        "pa": 64
      }
    },
    {
      "name": "Kathryn Copperthite",
      "jerseyNumber": 16,
      "classYear": "Sophomore",
      "position": "1B",
      "bats": "R",
      "season": {
        "year": 2026,
        "name": "Copperthite, Kathryn",
        "avg": 0.25,
        "ops": 0.65,
        "gp": 8,
        "gs": 0,
        "ab": 4,
        "r": 0,
        "h": 1,
        "doubles": 0,
        "triples": 0,
        "hr": 0,
        "rbi": 1,
        "tb": 1,
        "slg": 0.25,
        "bb": 1,
        "hbp": 0,
        "so": 2,
        "gdp": 0,
        "obp": 0.4,
        "sf": 0,
        "sh": 0,
        "sb": 0,
        "sbAtt": 0,
        "woba": 0.28,
        "pa": 5
      }
    },
    {
      "name": "Amber Arcand",
      "jerseyNumber": 33,
      "classYear": "Senior",
      "position": "RHP/OF",
      "bats": "R",
      "season": {
        "year": 2026,
        "name": "Arcand, Amber",
        "avg": 0.269,
        "ops": 0.675,
        "gp": 31,
        "gs": 31,
        "ab": 93,
        "r": 17,
        "h": 25,
        "doubles": 5,
        "triples": 0,
        "hr": 0,
        "rbi": 13,
        "tb": 30,
        "slg": 0.323,
        "bb": 12,
        "hbp": 0,
        "so": 8,
        "gdp": 0,
        "obp": 0.352,
        "sf": 0,
        "sh": 4,
        "sb": 3,
        "sbAtt": 3,
        "woba": 0.275,
        "pa": 109
      }
    },
    {
      "name": "Riley Dolan",
      "jerseyNumber": 12,
      "classYear": "Senior",
      "position": "C",
      "bats": "R",
      "season": {
        "year": 2026,
        "name": "Dolan, Riley",
        "avg": 0.25,
        "ops": 0.564,
        "gp": 28,
        "gs": 28,
        "ab": 76,
        "r": 4,
        "h": 19,
        "doubles": 3,
        "triples": 0,
        "hr": 0,
        "rbi": 5,
        "tb": 22,
        "slg": 0.289,
        "bb": 3,
        "hbp": 0,
        "so": 12,
        "gdp": 0,
        "obp": 0.275,
        "sf": 1,
        "sh": 2,
        "sb": 1,
        "sbAtt": 1,
        "woba": 0.238,
        "pa": 82
      }
    },
    {
      "name": "Alexandra Anquillare",
      "jerseyNumber": 10,
      "classYear": "First Year",
      "position": "OF",
      "bats": "R",
      "season": {
        "year": 2026,
        "name": "Anquillare, Alexandra",
        "avg": 0.214,
        "ops": 0.571,
        "gp": 10,
        "gs": 3,
        "ab": 14,
        "r": 1,
        "h": 3,
        "doubles": 2,
        "triples": 0,
        "hr": 0,
        "rbi": 4,
        "tb": 5,
        "slg": 0.357,
        "bb": 0,
        "hbp": 0,
        "so": 2,
        "gdp": 0,
        "obp": 0.214,
        "sf": 0,
        "sh": 0,
        "sb": 0,
        "sbAtt": 0,
        "woba": 0.236,
        "pa": 14
      }
    },
    {
      "name": "Gabby Reinbold",
      "jerseyNumber": 1,
      "classYear": "Junior",
      "position": "OF",
      "bats": "R",
      "season": {
        "year": 2026,
        "name": "Reinbold, Gabby",
        "avg": 0.224,
        "ops": 0.555,
        "gp": 28,
        "gs": 28,
        "ab": 67,
        "r": 4,
        "h": 15,
        "doubles": 1,
        "triples": 0,
        "hr": 0,
        "rbi": 8,
        "tb": 16,
        "slg": 0.239,
        "bb": 7,
        "hbp": 2,
        "so": 15,
        "gdp": 1,
        "obp": 0.316,
        "sf": 0,
        "sh": 2,
        "sb": 1,
        "sbAtt": 1,
        "woba": 0.235,
        "pa": 78
      }
    },
    {
      "name": "Julia  Miller",
      "jerseyNumber": 4,
      "classYear": "First Year",
      "position": "OF",
      "bats": "L",
      "season": {
        "year": 2026,
        "name": "Miller, Julia",
        "avg": 0.257,
        "ops": 0.578,
        "gp": 30,
        "gs": 30,
        "ab": 74,
        "r": 12,
        "h": 19,
        "doubles": 0,
        "triples": 0,
        "hr": 0,
        "rbi": 9,
        "tb": 19,
        "slg": 0.257,
        "bb": 7,
        "hbp": 0,
        "so": 12,
        "gdp": 1,
        "obp": 0.321,
        "sf": 0,
        "sh": 7,
        "sb": 5,
        "sbAtt": 5,
        "woba": 0.234,
        "pa": 88
      }
    },
    {
      "name": "Madi Miller",
      "jerseyNumber": 28,
      "classYear": "Sophomore",
      "position": "C/3B",
      "bats": "R",
      "season": {
        "year": 2026,
        "name": "Miller, Madi",
        "avg": 0.2,
        "ops": 0.517,
        "gp": 12,
        "gs": 2,
        "ab": 15,
        "r": 1,
        "h": 3,
        "doubles": 1,
        "triples": 0,
        "hr": 0,
        "rbi": 2,
        "tb": 4,
        "slg": 0.267,
        "bb": 1,
        "hbp": 0,
        "so": 1,
        "gdp": 0,
        "obp": 0.25,
        "sf": 0,
        "sh": 0,
        "sb": 0,
        "sbAtt": 0,
        "woba": 0.219,
        "pa": 16
      }
    },
    {
      "name": "Maggie Caron",
      "jerseyNumber": 18,
      "classYear": "Senior",
      "position": "IF",
      "bats": "R",
      "season": {
        "year": 2026,
        "name": "Caron, Maggie",
        "avg": 0.176,
        "ops": 0.439,
        "gp": 8,
        "gs": 7,
        "ab": 17,
        "r": 4,
        "h": 3,
        "doubles": 0,
        "triples": 0,
        "hr": 0,
        "rbi": 1,
        "tb": 3,
        "slg": 0.176,
        "bb": 2,
        "hbp": 0,
        "so": 2,
        "gdp": 0,
        "obp": 0.263,
        "sf": 0,
        "sh": 1,
        "sb": 0,
        "sbAtt": 0,
        "woba": 0.185,
        "pa": 20
      }
    },
    {
      "name": "Brittany Dost",
      "jerseyNumber": 23,
      "classYear": "Senior",
      "position": "RHP/1B",
      "bats": "R",
      "season": {
        "year": 2026,
        "name": "Dost, Brittany",
        "avg": 0.154,
        "ops": 0.395,
        "gp": 19,
        "gs": 17,
        "ab": 26,
        "r": 1,
        "h": 4,
        "doubles": 0,
        "triples": 0,
        "hr": 0,
        "rbi": 0,
        "tb": 4,
        "slg": 0.154,
        "bb": 3,
        "hbp": 0,
        "so": 5,
        "gdp": 1,
        "obp": 0.241,
        "sf": 0,
        "sh": 1,
        "sb": 0,
        "sbAtt": 1,
        "woba": 0.17,
        "pa": 30
      }
    },
    {
      "name": "Lexi Falcioni",
      "jerseyNumber": 13,
      "classYear": "First Year",
      "position": "IF",
      "bats": "R",
      "season": {
        "year": 2026,
        "name": "Falcioni, Lexi",
        "avg": 0.115,
        "ops": 0.354,
        "gp": 14,
        "gs": 10,
        "ab": 26,
        "r": 2,
        "h": 3,
        "doubles": 1,
        "triples": 0,
        "hr": 0,
        "rbi": 2,
        "tb": 4,
        "slg": 0.154,
        "bb": 3,
        "hbp": 0,
        "so": 3,
        "gdp": 0,
        "obp": 0.2,
        "sf": 1,
        "sh": 3,
        "sb": 1,
        "sbAtt": 1,
        "woba": 0.136,
        "pa": 33
      }
    },
    {
      "name": "Lauren Kelley",
      "jerseyNumber": 5,
      "classYear": "First Year",
      "position": "OF",
      "bats": "R",
      "season": {
        "year": 2026,
        "name": "Kelley, Lauren",
        "avg": 0,
        "ops": 0,
        "gp": 12,
        "gs": 0,
        "ab": 0,
        "r": 3,
        "h": 0,
        "doubles": 0,
        "triples": 0,
        "hr": 0,
        "rbi": 0,
        "tb": 0,
        "slg": 0,
        "bb": 0,
        "hbp": 0,
        "so": 0,
        "gdp": 0,
        "obp": 0,
        "sf": 0,
        "sh": 0,
        "sb": 1,
        "sbAtt": 1,
        "woba": 0,
        "pa": 0
      }
    },
    {
      "name": "Alli Wisnouskas",
      "jerseyNumber": 9,
      "classYear": "Sophomore",
      "position": "OF",
      "bats": "L",
      "season": {
        "year": 2026,
        "name": "Wisnouskas, Alli",
        "avg": 0,
        "ops": 0,
        "gp": 2,
        "gs": 1,
        "ab": 1,
        "r": 1,
        "h": 0,
        "doubles": 0,
        "triples": 0,
        "hr": 0,
        "rbi": 0,
        "tb": 0,
        "slg": 0,
        "bb": 0,
        "hbp": 0,
        "so": 0,
        "gdp": 0,
        "obp": 0,
        "sf": 0,
        "sh": 0,
        "sb": 0,
        "sbAtt": 0,
        "woba": 0,
        "pa": 1
      }
    }
  ]
}