{
  "seasonStats": [
    {
      "name": "Brittingham, Gen",
      "ab": 108,
      "h": 55,
      "doubles": 18,
      "triples": 2,
      "hr": 3,
      "bb": 3,
      "hbp": 0,
      "sf": 2,
      "sh": 0
    },
    {
      "name": "Smith, Kendall",
      "ab": 112,
      "h": 44,
      "doubles": 10,
      "triples": 0,
      "hr": 2,
      "bb": 5,
      "hbp": 2,
      "sf": 0,
      "sh": 5
    },
    {
      "name": "Hensch, Marisa",
      "ab": 100,
      "h": 37,
      "doubles": 9,
      "triples": 0,
      "hr": 2,
      "bb": 11,
      "hbp": 1,
      "sf": 1,
      "sh": 3
    },
    {
      "name": "Oliver, Kalei",
      "ab": 94,
      "h": 29,
      "doubles": 6,
      "triples": 0,
      "hr": 0,
      "bb": 7,
      "hbp": 0,
      "sf": 0,
      "sh": 4
    },
    {
      "name": "Brown, Autumn",
      "ab": 80,
      "h": 24,
      "doubles": 7,
      "triples": 1,
      "hr": 1,
      "bb": 2,
      "hbp": 0,
      "sf": 0,
      "sh": 2
    },
    {
      "name": "Griffin, Julianne",
      "ab": 86,
      "h": 21,
      "doubles": 6,
      "triples": 0,
      "hr": 2,
      "bb": 11,
      "hbp": 0,
      "sf": 1,
      "sh": 4
    },
    {
      "name": "Moniz, Hayley",
      "ab": 78,
      "h": 17,
      "doubles": 5,
      "triples": 0,
      "hr": 1,
      "bb": 12,
      "hbp": 0,
      "sf": 2,
      "sh": 3
    },
    {
      "name": "Hana, Alyssa",
      "ab": 93,
      "h": 16,
      "doubles": 2,
      "triples": 0,
      "hr": 0,
      "bb": 2,
      "hbp": 2,
      "sf": 0,
      "sh": 24
    },
    {
      "name": "Chin, Holly",
      "ab": 41,
      "h": 10,
      "doubles": 1,
      "triples": 0,
      "hr": 0,
      "bb": 6,
      "hbp": 1,
      "sf": 0,
      "sh": 1
    },
    {
      "name": "O'Shea, Jill",
      "ab": 53,
      "h": 8,
      "doubles": 1,
      "triples": 0,
      "hr": 0,
      "bb": 5,
      "hbp": 0,
      "sf": 0,
      "sh": 4
    },
    {
      "name": "Cheskin, Lucy",
      "ab": 13,
      "h": 0,
      "doubles": 0,
      "triples": 0,
      "hr": 0,
      "bb": 2,
      "hbp": 0,
      "sf": 0,
      "sh": 3
    },
    {
      "name": "Kawabata, Tatum",
      "ab": 5,
      "h": 0,
      "doubles": 0,
      "triples": 0,
      "hr": 0,
      "bb": 0,
      "hbp": 0,
      "sf": 0,
      "sh": 2
    },
    {
      "name": "Gordon, Caitlin",
      "ab": 3,
      "h": 0,
      "doubles": 0,
      "triples": 0,
      "hr": 0,
      "bb": 1,
      "hbp": 0,
      "sf": 0,
      "sh": 0
    }
  ],
  "boxscores": [
    {
      "date": "3/22/2019",
      "opponent": "Geneseo",
      "url": "https://wellesleyblue.com/sports/softball/stats/2019/geneseo/boxscore/968",
      "playerStats": [
        {
          "name": "Moniz, Hayley",
          "ab": 3,
          "h": 1,
          "doubles": 0,
          "triples": 0,
          "hr": 0,
          "bb": 0,
          "hbp": 0,
          "sf": 0,
          "sh": 0
        },
        {
          "name": "Hana, Alyssa",
          "ab": 2,
          "h": 1,
          "doubles": 0,
          "triples": 0,
          "hr": 0,
          "bb": 0,
          "hbp": 0,
          "sf": 0,
          "sh": 1
        },
        {
          "name": "Hensch, Marisa",
          "ab": 3,
          "h": 0,
          "doubles": 0,
          "triples": 0,
          "hr": 0,
          "bb": 0,
          "hbp": 0,
          "sf": 0,
          "sh": 0
        },
        {
          "name": "Brittingham, Gen",
          "ab": 3,
          "h": 2,
          "doubles": 0,
          "triples": 1,
          "hr": 0,
          "bb": 0,
          "hbp": 0,
          "sf": 0,
          "sh": 0
        },
        {
          "name": "Brown, Autumn",
          "ab": 3,
          "h": 1,
          "doubles": 1,
          "triples": 0,
          "hr": 0,
          "bb": 0,
          "hbp": 0,
          "sf": 0,
          "sh": 0
        },
        {
          "name": "Smith, Kendall",
          "ab": 3,
          "h": 1,
          "doubles": 0,
          "triples": 0,
          "hr": 0,
          "bb": 0,
          "hbp": 0,
          "sf": 0,
          "sh": 0
        },
        {
          "name": "Oliver, Kalei",
          "ab": 1,
          "h": 0,
          "doubles": 0,
          "triples": 0,
          "hr": 0,
          "bb": 1,
          "hbp": 0,
          "sf": 0,
          "sh": 1
        },
        {
          "name": "Griffin, Julianne",
          "ab": 3,
          "h": 1,
          "doubles": 1,
          "triples": 0,
          "hr": 0,
          "bb": 0,
          "hbp": 0,
          "sf": 0,
          "sh": 0
        },
        {
          "name": "Chin, Holly",
          "ab": 2,
          "h": 0,
          "doubles": 0,
          "triples": 0,
          "hr": 0,
          "bb": 0,
          "hbp": 0,
          "sf": 0,
          "sh": 0
        },
        {
          "name": "Hopper, Sydney",
          "ab": 0,
          "h": 0,
          "doubles": 0,
          "triples": 0,
          "hr": 0,
          "bb": 0,
          "hbp": 0,
          "sf": 0,
          "sh": 0
        }
      ]
    },
    {
      "date": "3/22/2019",
      "opponent": "Trinity Conn ",
      "url": "https://wellesleyblue.com/sports/softball/stats/2019/trinity-conn-/boxscore/969",
      "playerStats": [
        {
          "name": "Moniz, Hayley",
          "ab": 3,
          "h": 0,
          "doubles": 0,
          "triples": 0,
          "hr": 0,
          "bb": 0,
          "hbp": 0,
          "sf": 0,
          "sh": 1
        },
        {
          "name": "Hana, Alyssa",
          "ab": 4,
          "h": 2,
          "doubles": 0,
          "triples": 0,
          "hr": 0,
          "bb": 0,
          "hbp": 0,
          "sf": 0,
          "sh": 0
        },
        {
          "name": "Hensch, Marisa",
          "ab": 3,
          "h": 0,
          "doubles": 0,
          "triples": 0,
          "hr": 0,
          "bb": 1,
          "hbp": 0,
          "sf": 0,
          "sh": 0
        },
        {
          "name": "Brittingham, Gen",
          "ab": 4,
          "h": 2,
          "doubles": 1,
          "triples": 0,
          "hr": 0,
          "bb": 0,
          "hbp": 0,
          "sf": 0,
          "sh": 0
        },
        {
          "name": "Brown, Autumn",
          "ab": 4,
          "h": 3,
          "doubles": 2,
          "triples": 0,
          "hr": 0,
          "bb": 0,
          "hbp": 0,
          "sf": 0,
          "sh": 0
        },
        {
          "name": "Cheskin, Lucy",
          "ab": 0,
          "h": 0,
          "doubles": 0,
          "triples": 0,
          "hr": 0,
          "bb": 0,
          "hbp": 0,
          "sf": 0,
          "sh": 0
        },
        {
          "name": "Smith, Kendall",
          "ab": 4,
          "h": 2,
          "doubles": 0,
          "triples": 0,
          "hr": 0,
          "bb": 0,
          "hbp": 0,
          "sf": 0,
          "sh": 0
        },
        {
          "name": "Oliver, Kalei",
          "ab": 3,
          "h": 1,
          "doubles": 0,
          "triples": 0,
          "hr": 0,
          "bb": 0,
          "hbp": 0,
          "sf": 0,
          "sh": 0
        },
        {
          "name": "O'Shea, Jill",
          "ab": 1,
          "h": 1,
          "doubles": 0,
          "triples": 0,
          "hr": 0,
          "bb": 0,
          "hbp": 0,
          "sf": 0,
          "sh": 0
        },
        {
          "name": "Griffin, Julianne",
          "ab": 4,
          "h": 1,
          "doubles": 0,
          "triples": 0,
          "hr": 0,
          "bb": 0,
          "hbp": 0,
          "sf": 0,
          "sh": 0
        },
        {
          "name": "Chin, Holly",
          "ab": 3,
          "h": 1,
          "doubles": 0,
          "triples": 0,
          "hr": 0,
          "bb": 1,
          "hbp": 0,
          "sf": 0,
          "sh": 0
        },
        {
          "name": "Gordon, Caitlin",
          "ab": 0,
          "h": 0,
          "doubles": 0,
          "triples": 0,
          "hr": 0,
          "bb": 0,
          "hbp": 0,
          "sf": 0,
          "sh": 0
        },
        {
          "name": "McMorrow, Haley",
          "ab": 0,
          "h": 0,
          "doubles": 0,
          "triples": 0,
          "hr": 0,
          "bb": 0,
          "hbp": 0,
          "sf": 0,
          "sh": 0
        }
      ]
    },
    {
      "date": "3/23/2019",
      "opponent": "Colby",
      "url": "https://wellesleyblue.com/sports/softball/stats/2019/colby/boxscore/970",
      "playerStats": [
        {
          "name": "Moniz, Hayley",
          "ab": 2,
          "h": 0,
          "doubles": 0,
          "triples": 0,
          "hr": 0,
          "bb": 1,
          "hbp": 0,
          "sf": 0,
          "sh": 1
        },
        {
          "name": "Hana, Alyssa",
          "ab": 3,
          "h": 2,
          "doubles": 0,
          "triples": 0,
          "hr": 0,
          "bb": 0,
          "hbp": 0,
          "sf": 0,
          "sh": 1
        },
        {
          "name": "Hensch, Marisa",
          "ab": 4,
          "h": 1,
          "doubles": 0,
          "triples": 0,
          "hr": 0,
          "bb": 0,
          "hbp": 0,
          "sf": 0,
          "sh": 0
        },
        {
          "name": "Brittingham, Gen",
          "ab": 4,
          "h": 2,
          "doubles": 0,
          "triples": 0,
          "hr": 0,
          "bb": 0,
          "hbp": 0,
          "sf": 0,
          "sh": 0
        },
        {
          "name": "Brown, Autumn",
          "ab": 4,
          "h": 2,
          "doubles": 1,
          "triples": 0,
          "hr": 0,
          "bb": 0,
          "hbp": 0,
          "sf": 0,
          "sh": 0
        },
        {
          "name": "Smith, Kendall",
          "ab": 4,
          "h": 2,
          "doubles": 1,
          "triples": 0,
          "hr": 0,
          "bb": 0,
          "hbp": 0,
          "sf": 0,
          "sh": 0
        },
        {
          "name": "O'Shea, Jill",
          "ab": 3,
          "h": 0,
          "doubles": 0,
          "triples": 0,
          "hr": 0,
          "bb": 0,
          "hbp": 0,
          "sf": 0,
          "sh": 0
        },
        {
          "name": "Griffin, Julianne",
          "ab": 3,
          "h": 1,
          "doubles": 0,
          "triples": 0,
          "hr": 0,
          "bb": 0,
          "hbp": 0,
          "sf": 0,
          "sh": 0
        },
        {
          "name": "Oliver, Kalei",
          "ab": 3,
          "h": 1,
          "doubles": 0,
          "triples": 0,
          "hr": 0,
          "bb": 0,
          "hbp": 0,
          "sf": 0,
          "sh": 0
        },
        {
          "name": "Cheskin, Lucy",
          "ab": 0,
          "h": 0,
          "doubles": 0,
          "triples": 0,
          "hr": 0,
          "bb": 0,
          "hbp": 0,
          "sf": 0,
          "sh": 0
        },
        {
          "name": "McMorrow, Haley",
          "ab": 0,
          "h": 0,
          "doubles": 0,
          "triples": 0,
          "hr": 0,
          "bb": 0,
          "hbp": 0,
          "sf": 0,
          "sh": 0
        }
      ]
    },
    {
      "date": "3/23/2019",
      "opponent": "Wis Stout",
      "url": "https://wellesleyblue.com/sports/softball/stats/2019/wis-stout/boxscore/971",
      "playerStats": [
        {
          "name": "Smith, Kendall",
          "ab": 2,
          "h": 0,
          "doubles": 0,
          "triples": 0,
          "hr": 0,
          "bb": 0,
          "hbp": 0,
          "sf": 0,
          "sh": 1
        },
        {
          "name": "Hana, Alyssa",
          "ab": 3,
          "h": 0,
          "doubles": 0,
          "triples": 0,
          "hr": 0,
          "bb": 0,
          "hbp": 0,
          "sf": 0,
          "sh": 0
        },
        {
          "name": "Hensch, Marisa",
          "ab": 1,
          "h": 0,
          "doubles": 0,
          "triples": 0,
          "hr": 0,
          "bb": 2,
          "hbp": 0,
          "sf": 0,
          "sh": 0
        },
        {
          "name": "Brittingham, Gen",
          "ab": 3,
          "h": 2,
          "doubles": 1,
          "triples": 0,
          "hr": 0,
          "bb": 0,
          "hbp": 0,
          "sf": 0,
          "sh": 0
        },
        {
          "name": "Brown, Autumn",
          "ab": 2,
          "h": 0,
          "doubles": 0,
          "triples": 0,
          "hr": 0,
          "bb": 0,
          "hbp": 0,
          "sf": 0,
          "sh": 0
        },
        {
          "name": "Chin, Holly",
          "ab": 1,
          "h": 0,
          "doubles": 0,
          "triples": 0,
          "hr": 0,
          "bb": 0,
          "hbp": 0,
          "sf": 0,
          "sh": 0
        },
        {
          "name": "O'Shea, Jill",
          "ab": 3,
          "h": 1,
          "doubles": 1,
          "triples": 0,
          "hr": 0,
          "bb": 0,
          "hbp": 0,
          "sf": 0,
          "sh": 0
        },
        {
          "name": "Moniz, Hayley",
          "ab": 2,
          "h": 0,
          "doubles": 0,
          "triples": 0,
          "hr": 0,
          "bb": 0,
          "hbp": 0,
          "sf": 0,
          "sh": 1
        },
        {
          "name": "Griffin, Julianne",
          "ab": 3,
          "h": 1,
          "doubles": 1,
          "triples": 0,
          "hr": 0,
          "bb": 0,
          "hbp": 0,
          "sf": 0,
          "sh": 0
        },
        {
          "name": "Cheskin, Lucy",
          "ab": 0,
          "h": 0,
          "doubles": 0,
          "triples": 0,
          "hr": 0,
          "bb": 0,
          "hbp": 0,
          "sf": 0,
          "sh": 0
        },
        {
          "name": "Oliver, Kalei",
          "ab": 2,
          "h": 1,
          "doubles": 1,
          "triples": 0,
          "hr": 0,
          "bb": 0,
          "hbp": 0,
          "sf": 0,
          "sh": 0
        },
        {
          "name": "Hopper, Sydney",
          "ab": 0,
          "h": 0,
          "doubles": 0,
          "triples": 0,
          "hr": 0,
          "bb": 0,
          "hbp": 0,
          "sf": 0,
          "sh": 0
        }
      ]
    },
    {
      "date": "3/24/2019",
      "opponent": "Wis Whitewater",
      "url": "https://wellesleyblue.com/sports/softball/stats/2019/wis-whitewater/boxscore/972",
      "playerStats": [
        {
          "name": "Smith, Kendall",
          "ab": 3,
          "h": 1,
          "doubles": 0,
          "triples": 0,
          "hr": 1,
          "bb": 0,
          "hbp": 0,
          "sf": 0,
          "sh": 0
        },
        {
          "name": "Hana, Alyssa",
          "ab": 3,
          "h": 0,
          "doubles": 0,
          "triples": 0,
          "hr": 0,
          "bb": 0,
          "hbp": 0,
          "sf": 0,
          "sh": 0
        },
        {
          "name": "Hensch, Marisa",
          "ab": 2,
          "h": 0,
          "doubles": 0,
          "triples": 0,
          "hr": 0,
          "bb": 1,
          "hbp": 0,
          "sf": 0,
          "sh": 0
        },
        {
          "name": "Brittingham, Gen",
          "ab": 3,
          "h": 0,
          "doubles": 0,
          "triples": 0,
          "hr": 0,
          "bb": 0,
          "hbp": 0,
          "sf": 0,
          "sh": 0
        },
        {
          "name": "O'Shea, Jill",
          "ab": 3,
          "h": 0,
          "doubles": 0,
          "triples": 0,
          "hr": 0,
          "bb": 0,
          "hbp": 0,
          "sf": 0,
          "sh": 0
        },
        {
          "name": "Griffin, Julianne",
          "ab": 2,
          "h": 0,
          "doubles": 0,
          "triples": 0,
          "hr": 0,
          "bb": 1,
          "hbp": 0,
          "sf": 0,
          "sh": 0
        },
        {
          "name": "Moniz, Hayley",
          "ab": 2,
          "h": 0,
          "doubles": 0,
          "triples": 0,
          "hr": 0,
          "bb": 0,
          "hbp": 0,
          "sf": 0,
          "sh": 0
        },
        {
          "name": "Cheskin, Lucy",
          "ab": 1,
          "h": 0,
          "doubles": 0,
          "triples": 0,
          "hr": 0,
          "bb": 0,
          "hbp": 0,
          "sf": 0,
          "sh": 0
        },
        {
          "name": "Chin, Holly",
          "ab": 1,
          "h": 0,
          "doubles": 0,
          "triples": 0,
          "hr": 0,
          "bb": 1,
          "hbp": 0,
          "sf": 0,
          "sh": 0
        },
        {
          "name": "Oliver, Kalei",
          "ab": 2,
          "h": 0,
          "doubles": 0,
          "triples": 0,
          "hr": 0,
          "bb": 0,
          "hbp": 0,
          "sf": 0,
          "sh": 0
        },
        {
          "name": "Hopper, Sydney",
          "ab": 0,
          "h": 0,
          "doubles": 0,
          "triples": 0,
          "hr": 0,
          "bb": 0,
          "hbp": 0,
          "sf": 0,
          "sh": 0
        },
        {
          "name": "Gordon, Caitlin",
          "ab": 0,
          "h": 0,
          "doubles": 0,
          "triples": 0,
          "hr": 0,
          "bb": 0,
          "hbp": 0,
          "sf": 0,
          "sh": 0
        }
      ]
    },
    {
      "date": "3/24/2019",
      "opponent": "Buffalo State",
      "url": "https://wellesleyblue.com/sports/softball/stats/2019/buffalo-state/boxscore/973",
      "playerStats": [
        {
          "name": "Smith, Kendall",
          "ab": 3,
          "h": 0,
          "doubles": 0,
          "triples": 0,
          "hr": 0,
          "bb": 1,
          "hbp": 0,
          "sf": 0,
          "sh": 0
        },
        {
          "name": "Hana, Alyssa",
          "ab": 2,
          "h": 0,
          "doubles": 0,
          "triples": 0,
          "hr": 0,
          "bb": 0,
          "hbp": 0,
          "sf": 0,
          "sh": 0
        },
        {
          "name": "Hensch, Marisa",
          "ab": 2,
          "h": 1,
          "doubles": 0,
          "triples": 0,
          "hr": 0,
          "bb": 0,
          "hbp": 0,
          "sf": 0,
          "sh": 1
        },
        {
          "name": "Brittingham, Gen",
          "ab": 2,
          "h": 1,
          "doubles": 1,
          "triples": 0,
          "hr": 0,
          "bb": 1,
          "hbp": 0,
          "sf": 0,
          "sh": 0
        },
        {
          "name": "O'Shea, Jill",
          "ab": 2,
          "h": 0,
          "doubles": 0,
          "triples": 0,
          "hr": 0,
          "bb": 1,
          "hbp": 0,
          "sf": 0,
          "sh": 0
        },
        {
          "name": "Griffin, Julianne",
          "ab": 3,
          "h": 1,
          "doubles": 0,
          "triples": 0,
          "hr": 0,
          "bb": 0,
          "hbp": 0,
          "sf": 0,
          "sh": 0
        },
        {
          "name": "Moniz, Hayley",
          "ab": 2,
          "h": 0,
          "doubles": 0,
          "triples": 0,
          "hr": 0,
          "bb": 1,
          "hbp": 0,
          "sf": 0,
          "sh": 0
        },
        {
          "name": "Chin, Holly",
          "ab": 2,
          "h": 1,
          "doubles": 0,
          "triples": 0,
          "hr": 0,
          "bb": 1,
          "hbp": 0,
          "sf": 0,
          "sh": 0
        },
        {
          "name": "Oliver, Kalei",
          "ab": 0,
          "h": 0,
          "doubles": 0,
          "triples": 0,
          "hr": 0,
          "bb": 0,
          "hbp": 0,
          "sf": 0,
          "sh": 0
        },
        {
          "name": "Cheskin, Lucy",
          "ab": 1,
          "h": 0,
          "doubles": 0,
          "triples": 0,
          "hr": 0,
          "bb": 0,
          "hbp": 0,
          "sf": 0,
          "sh": 2
        },
        {
          "name": "Gordon, Caitlin",
          "ab": 0,
          "h": 0,
          "doubles": 0,
          "triples": 0,
          "hr": 0,
          "bb": 0,
          "hbp": 0,
          "sf": 0,
          "sh": 0
        }
      ]
    },
    {
      "date": "3/26/2019",
      "opponent": "Thomas Me ",
      "url": "https://wellesleyblue.com/sports/softball/stats/2019/thomas-me-/boxscore/974",
      "playerStats": [
        {
          "name": "Smith, Kendall",
          "ab": 3,
          "h": 2,
          "doubles": 1,
          "triples": 0,
          "hr": 0,
          "bb": 0,
          "hbp": 0,
          "sf": 0,
          "sh": 0
        },
        {
          "name": "Hana, Alyssa",
          "ab": 2,
          "h": 0,
          "doubles": 0,
          "triples": 0,
          "hr": 0,
          "bb": 0,
          "hbp": 0,
          "sf": 0,
          "sh": 1
        },
        {
          "name": "Hensch, Marisa",
          "ab": 2,
          "h": 2,
          "doubles": 0,
          "triples": 0,
          "hr": 0,
          "bb": 1,
          "hbp": 0,
          "sf": 0,
          "sh": 0
        },
        {
          "name": "Brittingham, Gen",
          "ab": 3,
          "h": 1,
          "doubles": 0,
          "triples": 0,
          "hr": 0,
          "bb": 0,
          "hbp": 0,
          "sf": 0,
          "sh": 0
        },
        {
          "name": "O'Shea, Jill",
          "ab": 2,
          "h": 0,
          "doubles": 0,
          "triples": 0,
          "hr": 0,
          "bb": 1,
          "hbp": 0,
          "sf": 0,
          "sh": 0
        },
        {
          "name": "Griffin, Julianne",
          "ab": 3,
          "h": 1,
          "doubles": 0,
          "triples": 0,
          "hr": 0,
          "bb": 0,
          "hbp": 0,
          "sf": 0,
          "sh": 0
        },
        {
          "name": "Moniz, Hayley",
          "ab": 3,
          "h": 0,
          "doubles": 0,
          "triples": 0,
          "hr": 0,
          "bb": 0,
          "hbp": 0,
          "sf": 0,
          "sh": 0
        },
        {
          "name": "Chin, Holly",
          "ab": 2,
          "h": 1,
          "doubles": 0,
          "triples": 0,
          "hr": 0,
          "bb": 1,
          "hbp": 0,
          "sf": 0,
          "sh": 0
        },
        {
          "name": "Oliver, Kalei",
          "ab": 2,
          "h": 0,
          "doubles": 0,
          "triples": 0,
          "hr": 0,
          "bb": 0,
          "hbp": 0,
          "sf": 0,
          "sh": 1
        },
        {
          "name": "Hopper, Sydney",
          "ab": 0,
          "h": 0,
          "doubles": 0,
          "triples": 0,
          "hr": 0,
          "bb": 0,
          "hbp": 0,
          "sf": 0,
          "sh": 0
        }
      ]
    },
    {
      "date": "3/26/2019",
      "opponent": "Oberlin",
      "url": "https://wellesleyblue.com/sports/softball/stats/2019/oberlin/boxscore/975",
      "playerStats": [
        {
          "name": "Smith, Kendall",
          "ab": 3,
          "h": 2,
          "doubles": 1,
          "triples": 0,
          "hr": 0,
          "bb": 2,
          "hbp": 0,
          "sf": 0,
          "sh": 0
        },
        {
          "name": "Hana, Alyssa",
          "ab": 4,
          "h": 3,
          "doubles": 2,
          "triples": 0,
          "hr": 0,
          "bb": 1,
          "hbp": 0,
          "sf": 0,
          "sh": 0
        },
        {
          "name": "Hensch, Marisa",
          "ab": 5,
          "h": 1,
          "doubles": 0,
          "triples": 0,
          "hr": 0,
          "bb": 0,
          "hbp": 0,
          "sf": 0,
          "sh": 0
        },
        {
          "name": "Brittingham, Gen",
          "ab": 4,
          "h": 3,
          "doubles": 1,
          "triples": 0,
          "hr": 0,
          "bb": 1,
          "hbp": 0,
          "sf": 0,
          "sh": 0
        },
        {
          "name": "O'Shea, Jill",
          "ab": 3,
          "h": 1,
          "doubles": 0,
          "triples": 0,
          "hr": 0,
          "bb": 2,
          "hbp": 0,
          "sf": 0,
          "sh": 0
        },
        {
          "name": "Oliver, Kalei",
          "ab": 5,
          "h": 3,
          "doubles": 0,
          "triples": 0,
          "hr": 0,
          "bb": 0,
          "hbp": 0,
          "sf": 0,
          "sh": 0
        },
        {
          "name": "Griffin, Julianne",
          "ab": 2,
          "h": 0,
          "doubles": 0,
          "triples": 0,
          "hr": 0,
          "bb": 2,
          "hbp": 0,
          "sf": 0,
          "sh": 1
        },
        {
          "name": "Cheskin, Lucy",
          "ab": 3,
          "h": 0,
          "doubles": 0,
          "triples": 0,
          "hr": 0,
          "bb": 1,
          "hbp": 0,
          "sf": 0,
          "sh": 0
        },
        {
          "name": "Kawabata, Tatum",
          "ab": 1,
          "h": 0,
          "doubles": 0,
          "triples": 0,
          "hr": 0,
          "bb": 0,
          "hbp": 0,
          "sf": 0,
          "sh": 0
        },
        {
          "name": "Moniz, Hayley",
          "ab": 2,
          "h": 0,
          "doubles": 0,
          "triples": 0,
          "hr": 0,
          "bb": 3,
          "hbp": 0,
          "sf": 0,
          "sh": 0
        },
        {
          "name": "Gordon, Caitlin",
          "ab": 0,
          "h": 0,
          "doubles": 0,
          "triples": 0,
          "hr": 0,
          "bb": 0,
          "hbp": 0,
          "sf": 0,
          "sh": 0
        },
        {
          "name": "Hopper, Sydney",
          "ab": 0,
          "h": 0,
          "doubles": 0,
          "triples": 0,
          "hr": 0,
          "bb": 0,
          "hbp": 0,
          "sf": 0,
          "sh": 0
        },
        {
          "name": "McMorrow, Haley",
          "ab": 0,
          "h": 0,
          "doubles": 0,
          "triples": 0,
          "hr": 0,
          "bb": 0,
          "hbp": 0,
          "sf": 0,
          "sh": 0
        }
      ]
    },
    {
      "date": "3/29/2019",
      "opponent": "Emerson",
      "url": "https://wellesleyblue.com/sports/softball/stats/2019/emerson/boxscore/976",
      "playerStats": [
        {
          "name": "Smith, Kendall",
          "ab": 2,
          "h": 0,
          "doubles": 0,
          "triples": 0,
          "hr": 0,
          "bb": 0,
          "hbp": 0,
          "sf": 0,
          "sh": 1
        },
        {
          "name": "Hana, Alyssa",
          "ab": 3,
          "h": 0,
          "doubles": 0,
          "triples": 0,
          "hr": 0,
          "bb": 0,
          "hbp": 0,
          "sf": 0,
          "sh": 0
        },
        {
          "name": "Hensch, Marisa",
          "ab": 2,
          "h": 0,
          "doubles": 0,
          "triples": 0,
          "hr": 0,
          "bb": 2,
          "hbp": 0,
          "sf": 0,
          "sh": 0
        },
        {
          "name": "Brittingham, Gen",
          "ab": 3,
          "h": 2,
          "doubles": 2,
          "triples": 0,
          "hr": 0,
          "bb": 1,
          "hbp": 0,
          "sf": 0,
          "sh": 0
        },
        {
          "name": "Oliver, Kalei",
          "ab": 2,
          "h": 2,
          "doubles": 0,
          "triples": 0,
          "hr": 0,
          "bb": 2,
          "hbp": 0,
          "sf": 0,
          "sh": 0
        },
        {
          "name": "O'Shea, Jill",
          "ab": 4,
          "h": 0,
          "doubles": 0,
          "triples": 0,
          "hr": 0,
          "bb": 0,
          "hbp": 0,
          "sf": 0,
          "sh": 0
        },
        {
          "name": "Griffin, Julianne",
          "ab": 4,
          "h": 0,
          "doubles": 0,
          "triples": 0,
          "hr": 0,
          "bb": 0,
          "hbp": 0,
          "sf": 0,
          "sh": 0
        },
        {
          "name": "Gordon, Caitlin",
          "ab": 1,
          "h": 0,
          "doubles": 0,
          "triples": 0,
          "hr": 0,
          "bb": 0,
          "hbp": 0,
          "sf": 0,
          "sh": 0
        },
        {
          "name": "Chin, Holly",
          "ab": 4,
          "h": 2,
          "doubles": 1,
          "triples": 0,
          "hr": 0,
          "bb": 0,
          "hbp": 0,
          "sf": 0,
          "sh": 0
        },
        {
          "name": "Moniz, Hayley",
          "ab": 3,
          "h": 0,
          "doubles": 0,
          "triples": 0,
          "hr": 0,
          "bb": 0,
          "hbp": 0,
          "sf": 0,
          "sh": 0
        },
        {
          "name": "Hopper, Sydney",
          "ab": 0,
          "h": 0,
          "doubles": 0,
          "triples": 0,
          "hr": 0,
          "bb": 0,
          "hbp": 0,
          "sf": 0,
          "sh": 0
        }
      ]
    },
    {
      "date": "3/30/2019",
      "opponent": "Babson",
      "url": "https://wellesleyblue.com/sports/softball/stats/2019/babson/boxscore/977",
      "playerStats": [
        {
          "name": "Smith, Kendall",
          "ab": 3,
          "h": 2,
          "doubles": 0,
          "triples": 0,
          "hr": 0,
          "bb": 0,
          "hbp": 0,
          "sf": 0,
          "sh": 0
        },
        {
          "name": "Hana, Alyssa",
          "ab": 2,
          "h": 0,
          "doubles": 0,
          "triples": 0,
          "hr": 0,
          "bb": 0,
          "hbp": 0,
          "sf": 0,
          "sh": 1
        },
        {
          "name": "Hensch, Marisa",
          "ab": 2,
          "h": 1,
          "doubles": 1,
          "triples": 0,
          "hr": 0,
          "bb": 1,
          "hbp": 0,
          "sf": 0,
          "sh": 0
        },
        {
          "name": "Brittingham, Gen",
          "ab": 3,
          "h": 1,
          "doubles": 0,
          "triples": 0,
          "hr": 0,
          "bb": 0,
          "hbp": 0,
          "sf": 0,
          "sh": 0
        },
        {
          "name": "Oliver, Kalei",
          "ab": 3,
          "h": 0,
          "doubles": 0,
          "triples": 0,
          "hr": 0,
          "bb": 0,
          "hbp": 0,
          "sf": 0,
          "sh": 0
        },
        {
          "name": "O'Shea, Jill",
          "ab": 3,
          "h": 0,
          "doubles": 0,
          "triples": 0,
          "hr": 0,
          "bb": 0,
          "hbp": 0,
          "sf": 0,
          "sh": 0
        },
        {
          "name": "Gordon, Caitlin",
          "ab": 2,
          "h": 0,
          "doubles": 0,
          "triples": 0,
          "hr": 0,
          "bb": 0,
          "hbp": 0,
          "sf": 0,
          "sh": 0
        },
        {
          "name": "Griffin, Julianne",
          "ab": 1,
          "h": 0,
          "doubles": 0,
          "triples": 0,
          "hr": 0,
          "bb": 1,
          "hbp": 0,
          "sf": 0,
          "sh": 0
        },
        {
          "name": "Chin, Holly",
          "ab": 2,
          "h": 0,
          "doubles": 0,
          "triples": 0,
          "hr": 0,
          "bb": 0,
          "hbp": 0,
          "sf": 0,
          "sh": 0
        },
        {
          "name": "Hopper, Sydney",
          "ab": 0,
          "h": 0,
          "doubles": 0,
          "triples": 0,
          "hr": 0,
          "bb": 0,
          "hbp": 0,
          "sf": 0,
          "sh": 0
        },
        {
          "name": "Moniz, Hayley",
          "ab": 0,
          "h": 0,
          "doubles": 0,
          "triples": 0,
          "hr": 0,
          "bb": 0,
          "hbp": 0,
          "sf": 0,
          "sh": 0
        }
      ]
    },
    {
      "date": "3/30/2019",
      "opponent": "Babson",
      "url": "https://wellesleyblue.com/sports/softball/stats/2019/babson/boxscore/978",
      "playerStats": [
        {
          "name": "Smith, Kendall",
          "ab": 5,
          "h": 3,
          "doubles": 0,
          "triples": 0,
          "hr": 1,
          "bb": 0,
          "hbp": 0,
          "sf": 0,
          "sh": 0
        },
        {
          "name": "Hana, Alyssa",
          "ab": 3,
          "h": 1,
          "doubles": 0,
          "triples": 0,
          "hr": 0,
          "bb": 0,
          "hbp": 0,
          "sf": 0,
          "sh": 1
        },
        {
          "name": "Hensch, Marisa",
          "ab": 4,
          "h": 2,
          "doubles": 0,
          "triples": 0,
          "hr": 1,
          "bb": 0,
          "hbp": 0,
          "sf": 0,
          "sh": 0
        },
        {
          "name": "Brittingham, Gen",
          "ab": 4,
          "h": 1,
          "doubles": 0,
          "triples": 0,
          "hr": 0,
          "bb": 0,
          "hbp": 0,
          "sf": 0,
          "sh": 0
        },
        {
          "name": "Oliver, Kalei",
          "ab": 3,
          "h": 0,
          "doubles": 0,
          "triples": 0,
          "hr": 0,
          "bb": 1,
          "hbp": 0,
          "sf": 0,
          "sh": 0
        },
        {
          "name": "O'Shea, Jill",
          "ab": 1,
          "h": 0,
          "doubles": 0,
          "triples": 0,
          "hr": 0,
          "bb": 0,
          "hbp": 0,
          "sf": 0,
          "sh": 0
        },
        {
          "name": "Cheskin, Lucy",
          "ab": 1,
          "h": 0,
          "doubles": 0,
          "triples": 0,
          "hr": 0,
          "bb": 1,
          "hbp": 0,
          "sf": 0,
          "sh": 1
        },
        {
          "name": "Moniz, Hayley",
          "ab": 4,
          "h": 1,
          "doubles": 1,
          "triples": 0,
          "hr": 0,
          "bb": 0,
          "hbp": 0,
          "sf": 0,
          "sh": 0
        },
        {
          "name": "Griffin, Julianne",
          "ab": 2,
          "h": 2,
          "doubles": 2,
          "triples": 0,
          "hr": 0,
          "bb": 2,
          "hbp": 0,
          "sf": 0,
          "sh": 0
        },
        {
          "name": "Chin, Holly",
          "ab": 2,
          "h": 1,
          "doubles": 0,
          "triples": 0,
          "hr": 0,
          "bb": 0,
          "hbp": 0,
          "sf": 0,
          "sh": 1
        },
        {
          "name": "McMorrow, Haley",
          "ab": 0,
          "h": 0,
          "doubles": 0,
          "triples": 0,
          "hr": 0,
          "bb": 0,
          "hbp": 0,
          "sf": 0,
          "sh": 0
        }
      ]
    },
    {
      "date": "4/3/2019",
      "opponent": "Brandeis",
      "url": "https://wellesleyblue.com/sports/softball/stats/2019/brandeis/boxscore/979",
      "playerStats": [
        {
          "name": "Smith, Kendall",
          "ab": 4,
          "h": 1,
          "doubles": 1,
          "triples": 0,
          "hr": 0,
          "bb": 0,
          "hbp": 0,
          "sf": 0,
          "sh": 0
        },
        {
          "name": "Hana, Alyssa",
          "ab": 3,
          "h": 0,
          "doubles": 0,
          "triples": 0,
          "hr": 0,
          "bb": 0,
          "hbp": 0,
          "sf": 0,
          "sh": 1
        },
        {
          "name": "Hensch, Marisa",
          "ab": 4,
          "h": 2,
          "doubles": 1,
          "triples": 0,
          "hr": 0,
          "bb": 0,
          "hbp": 0,
          "sf": 0,
          "sh": 0
        },
        {
          "name": "Brittingham, Gen",
          "ab": 3,
          "h": 2,
          "doubles": 0,
          "triples": 0,
          "hr": 0,
          "bb": 0,
          "hbp": 0,
          "sf": 0,
          "sh": 0
        },
        {
          "name": "Brown, Autumn",
          "ab": 3,
          "h": 0,
          "doubles": 0,
          "triples": 0,
          "hr": 0,
          "bb": 0,
          "hbp": 0,
          "sf": 0,
          "sh": 0
        },
        {
          "name": "Oliver, Kalei",
          "ab": 3,
          "h": 0,
          "doubles": 0,
          "triples": 0,
          "hr": 0,
          "bb": 0,
          "hbp": 0,
          "sf": 0,
          "sh": 0
        },
        {
          "name": "Griffin, Julianne",
          "ab": 2,
          "h": 0,
          "doubles": 0,
          "triples": 0,
          "hr": 0,
          "bb": 1,
          "hbp": 0,
          "sf": 0,
          "sh": 0
        },
        {
          "name": "Moniz, Hayley",
          "ab": 2,
          "h": 1,
          "doubles": 0,
          "triples": 0,
          "hr": 0,
          "bb": 1,
          "hbp": 0,
          "sf": 0,
          "sh": 0
        },
        {
          "name": "Chin, Holly",
          "ab": 3,
          "h": 1,
          "doubles": 0,
          "triples": 0,
          "hr": 0,
          "bb": 0,
          "hbp": 0,
          "sf": 0,
          "sh": 0
        },
        {
          "name": "Hopper, Sydney",
          "ab": 0,
          "h": 0,
          "doubles": 0,
          "triples": 0,
          "hr": 0,
          "bb": 0,
          "hbp": 0,
          "sf": 0,
          "sh": 0
        }
      ]
    },
    {
      "date": "4/3/2019",
      "opponent": "Brandeis",
      "url": "https://wellesleyblue.com/sports/softball/stats/2019/brandeis/boxscore/980",
      "playerStats": [
        {
          "name": "Smith, Kendall",
          "ab": 3,
          "h": 1,
          "doubles": 1,
          "triples": 0,
          "hr": 0,
          "bb": 0,
          "hbp": 0,
          "sf": 0,
          "sh": 1
        },
        {
          "name": "Hana, Alyssa",
          "ab": 3,
          "h": 0,
          "doubles": 0,
          "triples": 0,
          "hr": 0,
          "bb": 0,
          "hbp": 0,
          "sf": 0,
          "sh": 1
        },
        {
          "name": "Hensch, Marisa",
          "ab": 3,
          "h": 0,
          "doubles": 0,
          "triples": 0,
          "hr": 0,
          "bb": 1,
          "hbp": 0,
          "sf": 0,
          "sh": 0
        },
        {
          "name": "Brittingham, Gen",
          "ab": 4,
          "h": 4,
          "doubles": 1,
          "triples": 0,
          "hr": 0,
          "bb": 0,
          "hbp": 0,
          "sf": 0,
          "sh": 0
        },
        {
          "name": "Brown, Autumn",
          "ab": 4,
          "h": 1,
          "doubles": 0,
          "triples": 0,
          "hr": 0,
          "bb": 0,
          "hbp": 0,
          "sf": 0,
          "sh": 0
        },
        {
          "name": "Oliver, Kalei",
          "ab": 4,
          "h": 3,
          "doubles": 1,
          "triples": 0,
          "hr": 0,
          "bb": 0,
          "hbp": 0,
          "sf": 0,
          "sh": 0
        },
        {
          "name": "Cheskin, Lucy",
          "ab": 0,
          "h": 0,
          "doubles": 0,
          "triples": 0,
          "hr": 0,
          "bb": 0,
          "hbp": 0,
          "sf": 0,
          "sh": 0
        },
        {
          "name": "Griffin, Julianne",
          "ab": 1,
          "h": 0,
          "doubles": 0,
          "triples": 0,
          "hr": 0,
          "bb": 2,
          "hbp": 0,
          "sf": 0,
          "sh": 1
        },
        {
          "name": "Kawabata, Tatum",
          "ab": 3,
          "h": 0,
          "doubles": 0,
          "triples": 0,
          "hr": 0,
          "bb": 0,
          "hbp": 0,
          "sf": 0,
          "sh": 1
        },
        {
          "name": "Chin, Holly",
          "ab": 3,
          "h": 0,
          "doubles": 0,
          "triples": 0,
          "hr": 0,
          "bb": 1,
          "hbp": 0,
          "sf": 0,
          "sh": 0
        },
        {
          "name": "McMorrow, Haley",
          "ab": 0,
          "h": 0,
          "doubles": 0,
          "triples": 0,
          "hr": 0,
          "bb": 0,
          "hbp": 0,
          "sf": 0,
          "sh": 0
        },
        {
          "name": "Moniz, Hayley",
          "ab": 0,
          "h": 0,
          "doubles": 0,
          "triples": 0,
          "hr": 0,
          "bb": 0,
          "hbp": 0,
          "sf": 0,
          "sh": 0
        }
      ]
    },
    {
      "date": "4/5/2019",
      "opponent": "Wheaton",
      "url": "https://wellesleyblue.com/sports/softball/stats/2019/wheaton/boxscore/981",
      "playerStats": [
        {
          "name": "Smith, Kendall",
          "ab": 2,
          "h": 1,
          "doubles": 0,
          "triples": 0,
          "hr": 0,
          "bb": 0,
          "hbp": 0,
          "sf": 0,
          "sh": 0
        },
        {
          "name": "Hana, Alyssa",
          "ab": 1,
          "h": 0,
          "doubles": 0,
          "triples": 0,
          "hr": 0,
          "bb": 0,
          "hbp": 0,
          "sf": 0,
          "sh": 1
        },
        {
          "name": "Hensch, Marisa",
          "ab": 2,
          "h": 1,
          "doubles": 0,
          "triples": 0,
          "hr": 0,
          "bb": 0,
          "hbp": 0,
          "sf": 0,
          "sh": 0
        },
        {
          "name": "Brittingham, Gen",
          "ab": 2,
          "h": 0,
          "doubles": 0,
          "triples": 0,
          "hr": 0,
          "bb": 0,
          "hbp": 0,
          "sf": 0,
          "sh": 0
        },
        {
          "name": "Brown, Autumn",
          "ab": 2,
          "h": 1,
          "doubles": 1,
          "triples": 0,
          "hr": 0,
          "bb": 0,
          "hbp": 0,
          "sf": 0,
          "sh": 0
        },
        {
          "name": "Oliver, Kalei",
          "ab": 2,
          "h": 0,
          "doubles": 0,
          "triples": 0,
          "hr": 0,
          "bb": 0,
          "hbp": 0,
          "sf": 0,
          "sh": 0
        },
        {
          "name": "Griffin, Julianne",
          "ab": 2,
          "h": 1,
          "doubles": 0,
          "triples": 0,
          "hr": 0,
          "bb": 0,
          "hbp": 0,
          "sf": 0,
          "sh": 0
        },
        {
          "name": "Moniz, Hayley",
          "ab": 2,
          "h": 0,
          "doubles": 0,
          "triples": 0,
          "hr": 0,
          "bb": 0,
          "hbp": 0,
          "sf": 0,
          "sh": 0
        },
        {
          "name": "Chin, Holly",
          "ab": 1,
          "h": 0,
          "doubles": 0,
          "triples": 0,
          "hr": 0,
          "bb": 0,
          "hbp": 0,
          "sf": 0,
          "sh": 0
        },
        {
          "name": "Gordon, Caitlin",
          "ab": 0,
          "h": 0,
          "doubles": 0,
          "triples": 0,
          "hr": 0,
          "bb": 0,
          "hbp": 0,
          "sf": 0,
          "sh": 0
        }
      ]
    },
    {
      "date": "4/5/2019",
      "opponent": "Wheaton",
      "url": "https://wellesleyblue.com/sports/softball/stats/2019/wheaton/boxscore/982",
      "playerStats": [
        {
          "name": "Smith, Kendall",
          "ab": 3,
          "h": 2,
          "doubles": 0,
          "triples": 0,
          "hr": 0,
          "bb": 0,
          "hbp": 0,
          "sf": 0,
          "sh": 0
        },
        {
          "name": "Hana, Alyssa",
          "ab": 2,
          "h": 0,
          "doubles": 0,
          "triples": 0,
          "hr": 0,
          "bb": 0,
          "hbp": 0,
          "sf": 0,
          "sh": 1
        },
        {
          "name": "Hensch, Marisa",
          "ab": 3,
          "h": 3,
          "doubles": 0,
          "triples": 0,
          "hr": 0,
          "bb": 0,
          "hbp": 0,
          "sf": 0,
          "sh": 0
        },
        {
          "name": "Brittingham, Gen",
          "ab": 3,
          "h": 2,
          "doubles": 2,
          "triples": 0,
          "hr": 0,
          "bb": 0,
          "hbp": 0,
          "sf": 0,
          "sh": 0
        },
        {
          "name": "Brown, Autumn",
          "ab": 3,
          "h": 0,
          "doubles": 0,
          "triples": 0,
          "hr": 0,
          "bb": 0,
          "hbp": 0,
          "sf": 0,
          "sh": 0
        },
        {
          "name": "Oliver, Kalei",
          "ab": 2,
          "h": 1,
          "doubles": 1,
          "triples": 0,
          "hr": 0,
          "bb": 0,
          "hbp": 0,
          "sf": 0,
          "sh": 0
        },
        {
          "name": "Griffin, Julianne",
          "ab": 2,
          "h": 0,
          "doubles": 0,
          "triples": 0,
          "hr": 0,
          "bb": 0,
          "hbp": 0,
          "sf": 0,
          "sh": 0
        },
        {
          "name": "Moniz, Hayley",
          "ab": 2,
          "h": 0,
          "doubles": 0,
          "triples": 0,
          "hr": 0,
          "bb": 0,
          "hbp": 0,
          "sf": 0,
          "sh": 0
        },
        {
          "name": "Cheskin, Lucy",
          "ab": 2,
          "h": 0,
          "doubles": 0,
          "triples": 0,
          "hr": 0,
          "bb": 0,
          "hbp": 0,
          "sf": 0,
          "sh": 0
        },
        {
          "name": "McMorrow, Haley",
          "ab": 0,
          "h": 0,
          "doubles": 0,
          "triples": 0,
          "hr": 0,
          "bb": 0,
          "hbp": 0,
          "sf": 0,
          "sh": 0
        },
        {
          "name": "Gordon, Caitlin",
          "ab": 0,
          "h": 0,
          "doubles": 0,
          "triples": 0,
          "hr": 0,
          "bb": 0,
          "hbp": 0,
          "sf": 0,
          "sh": 0
        }
      ]
    },
    {
      "date": "4/6/2019",
      "opponent": "Smith",
      "url": "https://wellesleyblue.com/sports/softball/stats/2019/smith/boxscore/983",
      "playerStats": [
        {
          "name": "Smith, Kendall",
          "ab": 3,
          "h": 1,
          "doubles": 0,
          "triples": 0,
          "hr": 0,
          "bb": 0,
          "hbp": 0,
          "sf": 0,
          "sh": 1
        },
        {
          "name": "Hana, Alyssa",
          "ab": 2,
          "h": 0,
          "doubles": 0,
          "triples": 0,
          "hr": 0,
          "bb": 0,
          "hbp": 0,
          "sf": 0,
          "sh": 2
        },
        {
          "name": "Hensch, Marisa",
          "ab": 4,
          "h": 2,
          "doubles": 1,
          "triples": 0,
          "hr": 0,
          "bb": 0,
          "hbp": 0,
          "sf": 0,
          "sh": 0
        },
        {
          "name": "Brittingham, Gen",
          "ab": 3,
          "h": 1,
          "doubles": 1,
          "triples": 0,
          "hr": 0,
          "bb": 0,
          "hbp": 0,
          "sf": 0,
          "sh": 0
        },
        {
          "name": "Oliver, Kalei",
          "ab": 3,
          "h": 3,
          "doubles": 1,
          "triples": 0,
          "hr": 0,
          "bb": 0,
          "hbp": 0,
          "sf": 0,
          "sh": 0
        },
        {
          "name": "Brown, Autumn",
          "ab": 3,
          "h": 1,
          "doubles": 0,
          "triples": 0,
          "hr": 0,
          "bb": 0,
          "hbp": 0,
          "sf": 0,
          "sh": 0
        },
        {
          "name": "Moniz, Hayley",
          "ab": 2,
          "h": 1,
          "doubles": 1,
          "triples": 0,
          "hr": 0,
          "bb": 0,
          "hbp": 0,
          "sf": 1,
          "sh": 0
        },
        {
          "name": "Griffin, Julianne",
          "ab": 3,
          "h": 1,
          "doubles": 0,
          "triples": 0,
          "hr": 0,
          "bb": 0,
          "hbp": 0,
          "sf": 0,
          "sh": 0
        },
        {
          "name": "Chin, Holly",
          "ab": 3,
          "h": 0,
          "doubles": 0,
          "triples": 0,
          "hr": 0,
          "bb": 0,
          "hbp": 0,
          "sf": 0,
          "sh": 0
        },
        {
          "name": "Hopper, Sydney",
          "ab": 0,
          "h": 0,
          "doubles": 0,
          "triples": 0,
          "hr": 0,
          "bb": 0,
          "hbp": 0,
          "sf": 0,
          "sh": 0
        }
      ]
    },
    {
      "date": "4/6/2019",
      "opponent": "Smith",
      "url": "https://wellesleyblue.com/sports/softball/stats/2019/smith/boxscore/984",
      "playerStats": [
        {
          "name": "Smith, Kendall",
          "ab": 3,
          "h": 3,
          "doubles": 0,
          "triples": 0,
          "hr": 0,
          "bb": 0,
          "hbp": 0,
          "sf": 0,
          "sh": 0
        },
        {
          "name": "Hana, Alyssa",
          "ab": 1,
          "h": 0,
          "doubles": 0,
          "triples": 0,
          "hr": 0,
          "bb": 0,
          "hbp": 0,
          "sf": 0,
          "sh": 2
        },
        {
          "name": "Hensch, Marisa",
          "ab": 3,
          "h": 3,
          "doubles": 2,
          "triples": 0,
          "hr": 0,
          "bb": 0,
          "hbp": 0,
          "sf": 0,
          "sh": 0
        },
        {
          "name": "Brittingham, Gen",
          "ab": 3,
          "h": 1,
          "doubles": 1,
          "triples": 0,
          "hr": 0,
          "bb": 0,
          "hbp": 0,
          "sf": 0,
          "sh": 0
        },
        {
          "name": "Oliver, Kalei",
          "ab": 3,
          "h": 1,
          "doubles": 0,
          "triples": 0,
          "hr": 0,
          "bb": 0,
          "hbp": 0,
          "sf": 0,
          "sh": 0
        },
        {
          "name": "Brown, Autumn",
          "ab": 2,
          "h": 1,
          "doubles": 0,
          "triples": 0,
          "hr": 1,
          "bb": 0,
          "hbp": 0,
          "sf": 0,
          "sh": 0
        },
        {
          "name": "Kawabata, Tatum",
          "ab": 1,
          "h": 0,
          "doubles": 0,
          "triples": 0,
          "hr": 0,
          "bb": 0,
          "hbp": 0,
          "sf": 0,
          "sh": 0
        },
        {
          "name": "Moniz, Hayley",
          "ab": 2,
          "h": 1,
          "doubles": 1,
          "triples": 0,
          "hr": 0,
          "bb": 0,
          "hbp": 0,
          "sf": 0,
          "sh": 0
        },
        {
          "name": "Gordon, Caitlin",
          "ab": 0,
          "h": 0,
          "doubles": 0,
          "triples": 0,
          "hr": 0,
          "bb": 1,
          "hbp": 0,
          "sf": 0,
          "sh": 0
        },
        {
          "name": "Griffin, Julianne",
          "ab": 2,
          "h": 1,
          "doubles": 1,
          "triples": 0,
          "hr": 0,
          "bb": 0,
          "hbp": 0,
          "sf": 0,
          "sh": 0
        },
        {
          "name": "Cheskin, Lucy",
          "ab": 1,
          "h": 0,
          "doubles": 0,
          "triples": 0,
          "hr": 0,
          "bb": 0,
          "hbp": 0,
          "sf": 0,
          "sh": 0
        },
        {
          "name": "Chin, Holly",
          "ab": 3,
          "h": 2,
          "doubles": 0,
          "triples": 0,
          "hr": 0,
          "bb": 0,
          "hbp": 0,
          "sf": 0,
          "sh": 0
        },
        {
          "name": "McMorrow, Haley",
          "ab": 0,
          "h": 0,
          "doubles": 0,
          "triples": 0,
          "hr": 0,
          "bb": 0,
          "hbp": 0,
          "sf": 0,
          "sh": 0
        }
      ]
    },
    {
      "date": "4/10/2019",
      "opponent": "Springfield College",
      "url": "https://wellesleyblue.com/sports/softball/stats/2019/springfield-college/boxscore/985",
      "playerStats": [
        {
          "name": "Smith, Kendall",
          "ab": 5,
          "h": 1,
          "doubles": 1,
          "triples": 0,
          "hr": 0,
          "bb": 0,
          "hbp": 0,
          "sf": 0,
          "sh": 1
        },
        {
          "name": "Hana, Alyssa",
          "ab": 5,
          "h": 1,
          "doubles": 0,
          "triples": 0,
          "hr": 0,
          "bb": 0,
          "hbp": 0,
          "sf": 0,
          "sh": 1
        },
        {
          "name": "Hensch, Marisa",
          "ab": 4,
          "h": 3,
          "doubles": 0,
          "triples": 0,
          "hr": 0,
          "bb": 0,
          "hbp": 0,
          "sf": 0,
          "sh": 1
        },
        {
          "name": "Cheskin, Lucy",
          "ab": 0,
          "h": 0,
          "doubles": 0,
          "triples": 0,
          "hr": 0,
          "bb": 0,
          "hbp": 0,
          "sf": 0,
          "sh": 0
        },
        {
          "name": "Brittingham, Gen",
          "ab": 5,
          "h": 3,
          "doubles": 0,
          "triples": 0,
          "hr": 1,
          "bb": 0,
          "hbp": 0,
          "sf": 0,
          "sh": 0
        },
        {
          "name": "Oliver, Kalei",
          "ab": 4,
          "h": 1,
          "doubles": 0,
          "triples": 0,
          "hr": 0,
          "bb": 0,
          "hbp": 0,
          "sf": 0,
          "sh": 1
        },
        {
          "name": "Brown, Autumn",
          "ab": 3,
          "h": 1,
          "doubles": 0,
          "triples": 0,
          "hr": 0,
          "bb": 1,
          "hbp": 0,
          "sf": 0,
          "sh": 1
        },
        {
          "name": "Moniz, Hayley",
          "ab": 2,
          "h": 1,
          "doubles": 0,
          "triples": 0,
          "hr": 0,
          "bb": 2,
          "hbp": 0,
          "sf": 1,
          "sh": 0
        },
        {
          "name": "Griffin, Julianne",
          "ab": 4,
          "h": 1,
          "doubles": 0,
          "triples": 0,
          "hr": 0,
          "bb": 0,
          "hbp": 0,
          "sf": 1,
          "sh": 0
        },
        {
          "name": "Chin, Holly",
          "ab": 4,
          "h": 1,
          "doubles": 0,
          "triples": 0,
          "hr": 0,
          "bb": 0,
          "hbp": 0,
          "sf": 0,
          "sh": 0
        },
        {
          "name": "Kawabata, Tatum",
          "ab": 0,
          "h": 0,
          "doubles": 0,
          "triples": 0,
          "hr": 0,
          "bb": 0,
          "hbp": 0,
          "sf": 0,
          "sh": 1
        },
        {
          "name": "Hopper, Sydney",
          "ab": 0,
          "h": 0,
          "doubles": 0,
          "triples": 0,
          "hr": 0,
          "bb": 0,
          "hbp": 0,
          "sf": 0,
          "sh": 0
        },
        {
          "name": "McMorrow, Haley",
          "ab": 0,
          "h": 0,
          "doubles": 0,
          "triples": 0,
          "hr": 0,
          "bb": 0,
          "hbp": 0,
          "sf": 0,
          "sh": 0
        }
      ]
    },
    {
      "date": "4/10/2019",
      "opponent": "Springfield College",
      "url": "https://wellesleyblue.com/sports/softball/stats/2019/springfield-college/boxscore/986",
      "playerStats": [
        {
          "name": "Smith, Kendall",
          "ab": 4,
          "h": 2,
          "doubles": 0,
          "triples": 0,
          "hr": 0,
          "bb": 0,
          "hbp": 0,
          "sf": 0,
          "sh": 0
        },
        {
          "name": "Hana, Alyssa",
          "ab": 3,
          "h": 0,
          "doubles": 0,
          "triples": 0,
          "hr": 0,
          "bb": 1,
          "hbp": 0,
          "sf": 0,
          "sh": 0
        },
        {
          "name": "Hensch, Marisa",
          "ab": 3,
          "h": 2,
          "doubles": 0,
          "triples": 0,
          "hr": 0,
          "bb": 0,
          "hbp": 0,
          "sf": 0,
          "sh": 0
        },
        {
          "name": "Brittingham, Gen",
          "ab": 2,
          "h": 0,
          "doubles": 0,
          "triples": 0,
          "hr": 0,
          "bb": 0,
          "hbp": 0,
          "sf": 1,
          "sh": 0
        },
        {
          "name": "Oliver, Kalei",
          "ab": 3,
          "h": 2,
          "doubles": 1,
          "triples": 0,
          "hr": 0,
          "bb": 0,
          "hbp": 0,
          "sf": 0,
          "sh": 0
        },
        {
          "name": "Brown, Autumn",
          "ab": 2,
          "h": 0,
          "doubles": 0,
          "triples": 0,
          "hr": 0,
          "bb": 0,
          "hbp": 0,
          "sf": 0,
          "sh": 1
        },
        {
          "name": "Moniz, Hayley",
          "ab": 2,
          "h": 0,
          "doubles": 0,
          "triples": 0,
          "hr": 0,
          "bb": 1,
          "hbp": 0,
          "sf": 0,
          "sh": 0
        },
        {
          "name": "Griffin, Julianne",
          "ab": 3,
          "h": 0,
          "doubles": 0,
          "triples": 0,
          "hr": 0,
          "bb": 0,
          "hbp": 0,
          "sf": 0,
          "sh": 0
        },
        {
          "name": "Chin, Holly",
          "ab": 2,
          "h": 0,
          "doubles": 0,
          "triples": 0,
          "hr": 0,
          "bb": 1,
          "hbp": 0,
          "sf": 0,
          "sh": 0
        },
        {
          "name": "McMorrow, Haley",
          "ab": 0,
          "h": 0,
          "doubles": 0,
          "triples": 0,
          "hr": 0,
          "bb": 0,
          "hbp": 0,
          "sf": 0,
          "sh": 0
        }
      ]
    },
    {
      "date": "4/12/2019",
      "opponent": "Mit",
      "url": "https://wellesleyblue.com/sports/softball/stats/2019/mit/boxscore/987",
      "playerStats": [
        {
          "name": "Smith, Kendall",
          "ab": 4,
          "h": 1,
          "doubles": 0,
          "triples": 0,
          "hr": 0,
          "bb": 0,
          "hbp": 0,
          "sf": 0,
          "sh": 0
        },
        {
          "name": "Hana, Alyssa",
          "ab": 3,
          "h": 0,
          "doubles": 0,
          "triples": 0,
          "hr": 0,
          "bb": 0,
          "hbp": 0,
          "sf": 0,
          "sh": 1
        },
        {
          "name": "Hensch, Marisa",
          "ab": 3,
          "h": 0,
          "doubles": 0,
          "triples": 0,
          "hr": 0,
          "bb": 1,
          "hbp": 0,
          "sf": 0,
          "sh": 0
        },
        {
          "name": "Brittingham, Gen",
          "ab": 4,
          "h": 3,
          "doubles": 0,
          "triples": 0,
          "hr": 0,
          "bb": 0,
          "hbp": 0,
          "sf": 0,
          "sh": 0
        },
        {
          "name": "Oliver, Kalei",
          "ab": 4,
          "h": 1,
          "doubles": 0,
          "triples": 0,
          "hr": 0,
          "bb": 0,
          "hbp": 0,
          "sf": 0,
          "sh": 0
        },
        {
          "name": "Brown, Autumn",
          "ab": 4,
          "h": 1,
          "doubles": 0,
          "triples": 0,
          "hr": 0,
          "bb": 0,
          "hbp": 0,
          "sf": 0,
          "sh": 0
        },
        {
          "name": "Moniz, Hayley",
          "ab": 2,
          "h": 1,
          "doubles": 0,
          "triples": 0,
          "hr": 0,
          "bb": 1,
          "hbp": 0,
          "sf": 0,
          "sh": 0
        },
        {
          "name": "Griffin, Julianne",
          "ab": 3,
          "h": 0,
          "doubles": 0,
          "triples": 0,
          "hr": 0,
          "bb": 0,
          "hbp": 0,
          "sf": 0,
          "sh": 0
        },
        {
          "name": "Chin, Holly",
          "ab": 2,
          "h": 0,
          "doubles": 0,
          "triples": 0,
          "hr": 0,
          "bb": 0,
          "hbp": 0,
          "sf": 0,
          "sh": 0
        },
        {
          "name": "O'Shea, Jill",
          "ab": 0,
          "h": 0,
          "doubles": 0,
          "triples": 0,
          "hr": 0,
          "bb": 1,
          "hbp": 0,
          "sf": 0,
          "sh": 0
        },
        {
          "name": "Hopper, Sydney",
          "ab": 0,
          "h": 0,
          "doubles": 0,
          "triples": 0,
          "hr": 0,
          "bb": 0,
          "hbp": 0,
          "sf": 0,
          "sh": 0
        },
        {
          "name": "McMorrow, Haley",
          "ab": 0,
          "h": 0,
          "doubles": 0,
          "triples": 0,
          "hr": 0,
          "bb": 0,
          "hbp": 0,
          "sf": 0,
          "sh": 0
        }
      ]
    },
    {
      "date": "4/12/2019",
      "opponent": "Mit",
      "url": "https://wellesleyblue.com/sports/softball/stats/2019/mit/boxscore/988",
      "playerStats": [
        {
          "name": "Smith, Kendall",
          "ab": 3,
          "h": 1,
          "doubles": 0,
          "triples": 0,
          "hr": 0,
          "bb": 0,
          "hbp": 0,
          "sf": 0,
          "sh": 0
        },
        {
          "name": "Hana, Alyssa",
          "ab": 2,
          "h": 0,
          "doubles": 0,
          "triples": 0,
          "hr": 0,
          "bb": 0,
          "hbp": 0,
          "sf": 0,
          "sh": 1
        },
        {
          "name": "Hensch, Marisa",
          "ab": 2,
          "h": 0,
          "doubles": 0,
          "triples": 0,
          "hr": 0,
          "bb": 0,
          "hbp": 0,
          "sf": 1,
          "sh": 0
        },
        {
          "name": "Brittingham, Gen",
          "ab": 3,
          "h": 1,
          "doubles": 0,
          "triples": 0,
          "hr": 0,
          "bb": 0,
          "hbp": 0,
          "sf": 0,
          "sh": 0
        },
        {
          "name": "Oliver, Kalei",
          "ab": 3,
          "h": 0,
          "doubles": 0,
          "triples": 0,
          "hr": 0,
          "bb": 0,
          "hbp": 0,
          "sf": 0,
          "sh": 0
        },
        {
          "name": "Cheskin, Lucy",
          "ab": 0,
          "h": 0,
          "doubles": 0,
          "triples": 0,
          "hr": 0,
          "bb": 0,
          "hbp": 0,
          "sf": 0,
          "sh": 0
        },
        {
          "name": "Brown, Autumn",
          "ab": 3,
          "h": 0,
          "doubles": 0,
          "triples": 0,
          "hr": 0,
          "bb": 0,
          "hbp": 0,
          "sf": 0,
          "sh": 0
        },
        {
          "name": "Moniz, Hayley",
          "ab": 3,
          "h": 0,
          "doubles": 0,
          "triples": 0,
          "hr": 0,
          "bb": 0,
          "hbp": 0,
          "sf": 0,
          "sh": 0
        },
        {
          "name": "Griffin, Julianne",
          "ab": 3,
          "h": 0,
          "doubles": 0,
          "triples": 0,
          "hr": 0,
          "bb": 0,
          "hbp": 0,
          "sf": 0,
          "sh": 0
        },
        {
          "name": "Chin, Holly",
          "ab": 1,
          "h": 0,
          "doubles": 0,
          "triples": 0,
          "hr": 0,
          "bb": 0,
          "hbp": 0,
          "sf": 0,
          "sh": 0
        },
        {
          "name": "O'Shea, Jill",
          "ab": 1,
          "h": 0,
          "doubles": 0,
          "triples": 0,
          "hr": 0,
          "bb": 0,
          "hbp": 0,
          "sf": 0,
          "sh": 0
        },
        {
          "name": "Gordon, Caitlin",
          "ab": 0,
          "h": 0,
          "doubles": 0,
          "triples": 0,
          "hr": 0,
          "bb": 0,
          "hbp": 0,
          "sf": 0,
          "sh": 0
        }
      ]
    },
    {
      "date": "4/17/2019",
      "opponent": "Emerson",
      "url": "https://wellesleyblue.com/sports/softball/stats/2019/emerson/boxscore/989",
      "playerStats": [
        {
          "name": "Smith, Kendall",
          "ab": 4,
          "h": 2,
          "doubles": 0,
          "triples": 0,
          "hr": 0,
          "bb": 0,
          "hbp": 0,
          "sf": 0,
          "sh": 0
        },
        {
          "name": "Hana, Alyssa",
          "ab": 4,
          "h": 1,
          "doubles": 0,
          "triples": 0,
          "hr": 0,
          "bb": 0,
          "hbp": 0,
          "sf": 0,
          "sh": 0
        },
        {
          "name": "Hensch, Marisa",
          "ab": 3,
          "h": 0,
          "doubles": 0,
          "triples": 0,
          "hr": 0,
          "bb": 0,
          "hbp": 0,
          "sf": 0,
          "sh": 0
        },
        {
          "name": "Brittingham, Gen",
          "ab": 3,
          "h": 1,
          "doubles": 1,
          "triples": 0,
          "hr": 0,
          "bb": 0,
          "hbp": 0,
          "sf": 0,
          "sh": 0
        },
        {
          "name": "Oliver, Kalei",
          "ab": 3,
          "h": 0,
          "doubles": 0,
          "triples": 0,
          "hr": 0,
          "bb": 0,
          "hbp": 0,
          "sf": 0,
          "sh": 0
        },
        {
          "name": "Brown, Autumn",
          "ab": 3,
          "h": 2,
          "doubles": 0,
          "triples": 1,
          "hr": 0,
          "bb": 0,
          "hbp": 0,
          "sf": 0,
          "sh": 0
        },
        {
          "name": "Chin, Holly",
          "ab": 0,
          "h": 0,
          "doubles": 0,
          "triples": 0,
          "hr": 0,
          "bb": 0,
          "hbp": 0,
          "sf": 0,
          "sh": 0
        },
        {
          "name": "Moniz, Hayley",
          "ab": 3,
          "h": 2,
          "doubles": 0,
          "triples": 0,
          "hr": 0,
          "bb": 0,
          "hbp": 0,
          "sf": 0,
          "sh": 0
        },
        {
          "name": "Griffin, Julianne",
          "ab": 2,
          "h": 0,
          "doubles": 0,
          "triples": 0,
          "hr": 0,
          "bb": 0,
          "hbp": 0,
          "sf": 0,
          "sh": 1
        },
        {
          "name": "Cheskin, Lucy",
          "ab": 0,
          "h": 0,
          "doubles": 0,
          "triples": 0,
          "hr": 0,
          "bb": 0,
          "hbp": 0,
          "sf": 0,
          "sh": 0
        },
        {
          "name": "O'Shea, Jill",
          "ab": 3,
          "h": 1,
          "doubles": 0,
          "triples": 0,
          "hr": 0,
          "bb": 0,
          "hbp": 0,
          "sf": 0,
          "sh": 0
        },
        {
          "name": "McMorrow, Haley",
          "ab": 0,
          "h": 0,
          "doubles": 0,
          "triples": 0,
          "hr": 0,
          "bb": 0,
          "hbp": 0,
          "sf": 0,
          "sh": 0
        },
        {
          "name": "Gordon, Caitlin",
          "ab": 0,
          "h": 0,
          "doubles": 0,
          "triples": 0,
          "hr": 0,
          "bb": 0,
          "hbp": 0,
          "sf": 0,
          "sh": 0
        }
      ]
    },
    {
      "date": "4/19/2019",
      "opponent": "Wpi",
      "url": "https://wellesleyblue.com/sports/softball/stats/2019/wpi/boxscore/990",
      "playerStats": [
        {
          "name": "Smith, Kendall",
          "ab": 3,
          "h": 0,
          "doubles": 0,
          "triples": 0,
          "hr": 0,
          "bb": 0,
          "hbp": 0,
          "sf": 0,
          "sh": 0
        },
        {
          "name": "Hana, Alyssa",
          "ab": 3,
          "h": 0,
          "doubles": 0,
          "triples": 0,
          "hr": 0,
          "bb": 0,
          "hbp": 0,
          "sf": 0,
          "sh": 0
        },
        {
          "name": "Hensch, Marisa",
          "ab": 3,
          "h": 1,
          "doubles": 1,
          "triples": 0,
          "hr": 0,
          "bb": 0,
          "hbp": 0,
          "sf": 0,
          "sh": 0
        },
        {
          "name": "Brittingham, Gen",
          "ab": 3,
          "h": 1,
          "doubles": 0,
          "triples": 1,
          "hr": 0,
          "bb": 0,
          "hbp": 0,
          "sf": 0,
          "sh": 0
        },
        {
          "name": "Oliver, Kalei",
          "ab": 3,
          "h": 0,
          "doubles": 0,
          "triples": 0,
          "hr": 0,
          "bb": 0,
          "hbp": 0,
          "sf": 0,
          "sh": 0
        },
        {
          "name": "Brown, Autumn",
          "ab": 2,
          "h": 0,
          "doubles": 0,
          "triples": 0,
          "hr": 0,
          "bb": 0,
          "hbp": 0,
          "sf": 0,
          "sh": 0
        },
        {
          "name": "Moniz, Hayley",
          "ab": 2,
          "h": 0,
          "doubles": 0,
          "triples": 0,
          "hr": 0,
          "bb": 0,
          "hbp": 0,
          "sf": 0,
          "sh": 0
        },
        {
          "name": "Griffin, Julianne",
          "ab": 2,
          "h": 0,
          "doubles": 0,
          "triples": 0,
          "hr": 0,
          "bb": 0,
          "hbp": 0,
          "sf": 0,
          "sh": 0
        },
        {
          "name": "Cheskin, Lucy",
          "ab": 2,
          "h": 0,
          "doubles": 0,
          "triples": 0,
          "hr": 0,
          "bb": 0,
          "hbp": 0,
          "sf": 0,
          "sh": 0
        },
        {
          "name": "Hopper, Sydney",
          "ab": 0,
          "h": 0,
          "doubles": 0,
          "triples": 0,
          "hr": 0,
          "bb": 0,
          "hbp": 0,
          "sf": 0,
          "sh": 0
        },
        {
          "name": "McMorrow, Haley",
          "ab": 0,
          "h": 0,
          "doubles": 0,
          "triples": 0,
          "hr": 0,
          "bb": 0,
          "hbp": 0,
          "sf": 0,
          "sh": 0
        }
      ]
    },
    {
      "date": "4/19/2019",
      "opponent": "Wpi",
      "url": "https://wellesleyblue.com/sports/softball/stats/2019/wpi/boxscore/991",
      "playerStats": [
        {
          "name": "Smith, Kendall",
          "ab": 4,
          "h": 1,
          "doubles": 0,
          "triples": 0,
          "hr": 0,
          "bb": 0,
          "hbp": 0,
          "sf": 0,
          "sh": 0
        },
        {
          "name": "Hana, Alyssa",
          "ab": 3,
          "h": 2,
          "doubles": 0,
          "triples": 0,
          "hr": 0,
          "bb": 0,
          "hbp": 0,
          "sf": 0,
          "sh": 1
        },
        {
          "name": "Hensch, Marisa",
          "ab": 4,
          "h": 2,
          "doubles": 0,
          "triples": 0,
          "hr": 1,
          "bb": 0,
          "hbp": 0,
          "sf": 0,
          "sh": 0
        },
        {
          "name": "Brittingham, Gen",
          "ab": 4,
          "h": 2,
          "doubles": 0,
          "triples": 0,
          "hr": 1,
          "bb": 0,
          "hbp": 0,
          "sf": 0,
          "sh": 0
        },
        {
          "name": "Oliver, Kalei",
          "ab": 4,
          "h": 0,
          "doubles": 0,
          "triples": 0,
          "hr": 0,
          "bb": 0,
          "hbp": 0,
          "sf": 0,
          "sh": 0
        },
        {
          "name": "Brown, Autumn",
          "ab": 3,
          "h": 2,
          "doubles": 0,
          "triples": 0,
          "hr": 0,
          "bb": 0,
          "hbp": 0,
          "sf": 0,
          "sh": 0
        },
        {
          "name": "Moniz, Hayley",
          "ab": 3,
          "h": 0,
          "doubles": 0,
          "triples": 0,
          "hr": 0,
          "bb": 0,
          "hbp": 0,
          "sf": 0,
          "sh": 0
        },
        {
          "name": "Griffin, Julianne",
          "ab": 3,
          "h": 1,
          "doubles": 0,
          "triples": 0,
          "hr": 0,
          "bb": 0,
          "hbp": 0,
          "sf": 0,
          "sh": 0
        },
        {
          "name": "Cheskin, Lucy",
          "ab": 2,
          "h": 0,
          "doubles": 0,
          "triples": 0,
          "hr": 0,
          "bb": 0,
          "hbp": 0,
          "sf": 0,
          "sh": 0
        },
        {
          "name": "O'Shea, Jill",
          "ab": 1,
          "h": 0,
          "doubles": 0,
          "triples": 0,
          "hr": 0,
          "bb": 0,
          "hbp": 0,
          "sf": 0,
          "sh": 0
        },
        {
          "name": "Gordon, Caitlin",
          "ab": 0,
          "h": 0,
          "doubles": 0,
          "triples": 0,
          "hr": 0,
          "bb": 0,
          "hbp": 0,
          "sf": 0,
          "sh": 0
        }
      ]
    },
    {
      "date": "4/23/2019",
      "opponent": "Clark University",
      "url": "https://wellesleyblue.com/sports/softball/stats/2019/clark-university/boxscore/992",
      "playerStats": [
        {
          "name": "Smith, Kendall",
          "ab": 4,
          "h": 1,
          "doubles": 0,
          "triples": 0,
          "hr": 0,
          "bb": 0,
          "hbp": 0,
          "sf": 0,
          "sh": 0
        },
        {
          "name": "Hana, Alyssa",
          "ab": 4,
          "h": 1,
          "doubles": 0,
          "triples": 0,
          "hr": 0,
          "bb": 0,
          "hbp": 0,
          "sf": 0,
          "sh": 0
        },
        {
          "name": "Hensch, Marisa",
          "ab": 3,
          "h": 1,
          "doubles": 0,
          "triples": 0,
          "hr": 0,
          "bb": 1,
          "hbp": 0,
          "sf": 0,
          "sh": 0
        },
        {
          "name": "Brittingham, Gen",
          "ab": 4,
          "h": 2,
          "doubles": 2,
          "triples": 0,
          "hr": 0,
          "bb": 0,
          "hbp": 0,
          "sf": 0,
          "sh": 0
        },
        {
          "name": "Oliver, Kalei",
          "ab": 4,
          "h": 0,
          "doubles": 0,
          "triples": 0,
          "hr": 0,
          "bb": 0,
          "hbp": 0,
          "sf": 0,
          "sh": 0
        },
        {
          "name": "Cheskin, Lucy",
          "ab": 0,
          "h": 0,
          "doubles": 0,
          "triples": 0,
          "hr": 0,
          "bb": 0,
          "hbp": 0,
          "sf": 0,
          "sh": 0
        },
        {
          "name": "Brown, Autumn",
          "ab": 3,
          "h": 1,
          "doubles": 0,
          "triples": 0,
          "hr": 0,
          "bb": 1,
          "hbp": 0,
          "sf": 0,
          "sh": 0
        },
        {
          "name": "Chin, Holly",
          "ab": 0,
          "h": 0,
          "doubles": 0,
          "triples": 0,
          "hr": 0,
          "bb": 0,
          "hbp": 0,
          "sf": 0,
          "sh": 0
        },
        {
          "name": "O'Shea, Jill",
          "ab": 1,
          "h": 0,
          "doubles": 0,
          "triples": 0,
          "hr": 0,
          "bb": 0,
          "hbp": 0,
          "sf": 0,
          "sh": 2
        },
        {
          "name": "Moniz, Hayley",
          "ab": 3,
          "h": 1,
          "doubles": 0,
          "triples": 0,
          "hr": 0,
          "bb": 0,
          "hbp": 0,
          "sf": 0,
          "sh": 0
        },
        {
          "name": "Griffin, Julianne",
          "ab": 3,
          "h": 2,
          "doubles": 0,
          "triples": 0,
          "hr": 1,
          "bb": 0,
          "hbp": 0,
          "sf": 0,
          "sh": 0
        }
      ]
    },
    {
      "date": "4/23/2019",
      "opponent": "Clark University",
      "url": "https://wellesleyblue.com/sports/softball/stats/2019/clark-university/boxscore/993",
      "playerStats": [
        {
          "name": "Smith, Kendall",
          "ab": 4,
          "h": 1,
          "doubles": 0,
          "triples": 0,
          "hr": 0,
          "bb": 0,
          "hbp": 0,
          "sf": 0,
          "sh": 0
        },
        {
          "name": "Hana, Alyssa",
          "ab": 3,
          "h": 0,
          "doubles": 0,
          "triples": 0,
          "hr": 0,
          "bb": 0,
          "hbp": 0,
          "sf": 0,
          "sh": 1
        },
        {
          "name": "Hensch, Marisa",
          "ab": 4,
          "h": 2,
          "doubles": 0,
          "triples": 0,
          "hr": 0,
          "bb": 0,
          "hbp": 0,
          "sf": 0,
          "sh": 0
        },
        {
          "name": "Brittingham, Gen",
          "ab": 4,
          "h": 4,
          "doubles": 1,
          "triples": 0,
          "hr": 0,
          "bb": 0,
          "hbp": 0,
          "sf": 0,
          "sh": 0
        },
        {
          "name": "Brown, Autumn",
          "ab": 4,
          "h": 0,
          "doubles": 0,
          "triples": 0,
          "hr": 0,
          "bb": 0,
          "hbp": 0,
          "sf": 0,
          "sh": 0
        },
        {
          "name": "Oliver, Kalei",
          "ab": 4,
          "h": 1,
          "doubles": 0,
          "triples": 0,
          "hr": 0,
          "bb": 0,
          "hbp": 0,
          "sf": 0,
          "sh": 0
        },
        {
          "name": "O'Shea, Jill",
          "ab": 2,
          "h": 1,
          "doubles": 0,
          "triples": 0,
          "hr": 0,
          "bb": 0,
          "hbp": 0,
          "sf": 0,
          "sh": 1
        },
        {
          "name": "Kawabata, Tatum",
          "ab": 0,
          "h": 0,
          "doubles": 0,
          "triples": 0,
          "hr": 0,
          "bb": 0,
          "hbp": 0,
          "sf": 0,
          "sh": 0
        },
        {
          "name": "Moniz, Hayley",
          "ab": 3,
          "h": 1,
          "doubles": 0,
          "triples": 0,
          "hr": 1,
          "bb": 0,
          "hbp": 0,
          "sf": 0,
          "sh": 0
        },
        {
          "name": "Griffin, Julianne",
          "ab": 3,
          "h": 0,
          "doubles": 0,
          "triples": 0,
          "hr": 0,
          "bb": 0,
          "hbp": 0,
          "sf": 0,
          "sh": 0
        },
        {
          "name": "Gordon, Caitlin",
          "ab": 0,
          "h": 0,
          "doubles": 0,
          "triples": 0,
          "hr": 0,
          "bb": 0,
          "hbp": 0,
          "sf": 0,
          "sh": 0
        },
        {
          "name": "Hopper, Sydney",
          "ab": 0,
          "h": 0,
          "doubles": 0,
          "triples": 0,
          "hr": 0,
          "bb": 0,
          "hbp": 0,
          "sf": 0,
          "sh": 0
        }
      ]
    },
    {
      "date": "4/24/2019",
      "opponent": "United States Coast Guard Academy",
      "url": "https://wellesleyblue.com/sports/softball/stats/2019/united-states-coast-guard-academy/boxscore/994",
      "playerStats": [
        {
          "name": "Smith, Kendall",
          "ab": 4,
          "h": 2,
          "doubles": 0,
          "triples": 0,
          "hr": 0,
          "bb": 1,
          "hbp": 0,
          "sf": 0,
          "sh": 0
        },
        {
          "name": "Hana, Alyssa",
          "ab": 4,
          "h": 1,
          "doubles": 0,
          "triples": 0,
          "hr": 0,
          "bb": 0,
          "hbp": 0,
          "sf": 0,
          "sh": 1
        },
        {
          "name": "Hensch, Marisa",
          "ab": 4,
          "h": 1,
          "doubles": 1,
          "triples": 0,
          "hr": 0,
          "bb": 0,
          "hbp": 0,
          "sf": 0,
          "sh": 0
        },
        {
          "name": "Brittingham, Gen",
          "ab": 4,
          "h": 1,
          "doubles": 0,
          "triples": 0,
          "hr": 0,
          "bb": 0,
          "hbp": 0,
          "sf": 0,
          "sh": 0
        },
        {
          "name": "Oliver, Kalei",
          "ab": 4,
          "h": 1,
          "doubles": 0,
          "triples": 0,
          "hr": 0,
          "bb": 0,
          "hbp": 0,
          "sf": 0,
          "sh": 0
        },
        {
          "name": "Brown, Autumn",
          "ab": 4,
          "h": 3,
          "doubles": 0,
          "triples": 0,
          "hr": 0,
          "bb": 0,
          "hbp": 0,
          "sf": 0,
          "sh": 0
        },
        {
          "name": "Chin, Holly",
          "ab": 0,
          "h": 0,
          "doubles": 0,
          "triples": 0,
          "hr": 0,
          "bb": 0,
          "hbp": 0,
          "sf": 0,
          "sh": 0
        },
        {
          "name": "O'Shea, Jill",
          "ab": 3,
          "h": 0,
          "doubles": 0,
          "triples": 0,
          "hr": 0,
          "bb": 0,
          "hbp": 0,
          "sf": 0,
          "sh": 1
        },
        {
          "name": "Moniz, Hayley",
          "ab": 4,
          "h": 3,
          "doubles": 1,
          "triples": 0,
          "hr": 0,
          "bb": 0,
          "hbp": 0,
          "sf": 0,
          "sh": 0
        },
        {
          "name": "Griffin, Julianne",
          "ab": 4,
          "h": 1,
          "doubles": 0,
          "triples": 0,
          "hr": 0,
          "bb": 0,
          "hbp": 0,
          "sf": 0,
          "sh": 0
        },
        {
          "name": "McMorrow, Haley",
          "ab": 0,
          "h": 0,
          "doubles": 0,
          "triples": 0,
          "hr": 0,
          "bb": 0,
          "hbp": 0,
          "sf": 0,
          "sh": 0
        }
      ]
    },
    {
      "date": "4/24/2019",
      "opponent": "United States Coast Guard Academy",
      "url": "https://wellesleyblue.com/sports/softball/stats/2019/united-states-coast-guard-academy/boxscore/995",
      "playerStats": [
        {
          "name": "Smith, Kendall",
          "ab": 5,
          "h": 3,
          "doubles": 1,
          "triples": 0,
          "hr": 0,
          "bb": 0,
          "hbp": 0,
          "sf": 0,
          "sh": 0
        },
        {
          "name": "Hana, Alyssa",
          "ab": 4,
          "h": 1,
          "doubles": 0,
          "triples": 0,
          "hr": 0,
          "bb": 0,
          "hbp": 0,
          "sf": 0,
          "sh": 1
        },
        {
          "name": "Hensch, Marisa",
          "ab": 5,
          "h": 2,
          "doubles": 1,
          "triples": 0,
          "hr": 0,
          "bb": 0,
          "hbp": 0,
          "sf": 0,
          "sh": 0
        },
        {
          "name": "Brittingham, Gen",
          "ab": 4,
          "h": 3,
          "doubles": 2,
          "triples": 0,
          "hr": 0,
          "bb": 0,
          "hbp": 0,
          "sf": 0,
          "sh": 0
        },
        {
          "name": "Oliver, Kalei",
          "ab": 3,
          "h": 1,
          "doubles": 1,
          "triples": 0,
          "hr": 0,
          "bb": 1,
          "hbp": 0,
          "sf": 0,
          "sh": 0
        },
        {
          "name": "Brown, Autumn",
          "ab": 4,
          "h": 0,
          "doubles": 0,
          "triples": 0,
          "hr": 0,
          "bb": 0,
          "hbp": 0,
          "sf": 0,
          "sh": 0
        },
        {
          "name": "O'Shea, Jill",
          "ab": 4,
          "h": 0,
          "doubles": 0,
          "triples": 0,
          "hr": 0,
          "bb": 0,
          "hbp": 0,
          "sf": 0,
          "sh": 0
        },
        {
          "name": "Moniz, Hayley",
          "ab": 3,
          "h": 1,
          "doubles": 0,
          "triples": 0,
          "hr": 0,
          "bb": 1,
          "hbp": 0,
          "sf": 0,
          "sh": 0
        },
        {
          "name": "Griffin, Julianne",
          "ab": 4,
          "h": 2,
          "doubles": 0,
          "triples": 0,
          "hr": 1,
          "bb": 0,
          "hbp": 0,
          "sf": 0,
          "sh": 0
        },
        {
          "name": "Gordon, Caitlin",
          "ab": 0,
          "h": 0,
          "doubles": 0,
          "triples": 0,
          "hr": 0,
          "bb": 0,
          "hbp": 0,
          "sf": 0,
          "sh": 0
        },
        {
          "name": "Hopper, Sydney",
          "ab": 0,
          "h": 0,
          "doubles": 0,
          "triples": 0,
          "hr": 0,
          "bb": 0,
          "hbp": 0,
          "sf": 0,
          "sh": 0
        }
      ]
    },
    {
      "date": "5/1/2019",
      "opponent": "Babson",
      "url": "https://wellesleyblue.com/sports/softball/stats/2019/babson/boxscore/996",
      "playerStats": [
        {
          "name": "Smith, Kendall",
          "ab": 4,
          "h": 3,
          "doubles": 2,
          "triples": 0,
          "hr": 0,
          "bb": 0,
          "hbp": 0,
          "sf": 0,
          "sh": 0
        },
        {
          "name": "Hana, Alyssa",
          "ab": 0,
          "h": 0,
          "doubles": 0,
          "triples": 0,
          "hr": 0,
          "bb": 0,
          "hbp": 0,
          "sf": 0,
          "sh": 3
        },
        {
          "name": "Hensch, Marisa",
          "ab": 2,
          "h": 0,
          "doubles": 0,
          "triples": 0,
          "hr": 0,
          "bb": 0,
          "hbp": 0,
          "sf": 0,
          "sh": 1
        },
        {
          "name": "Brittingham, Gen",
          "ab": 3,
          "h": 1,
          "doubles": 0,
          "triples": 0,
          "hr": 0,
          "bb": 0,
          "hbp": 0,
          "sf": 0,
          "sh": 0
        },
        {
          "name": "Oliver, Kalei",
          "ab": 3,
          "h": 0,
          "doubles": 0,
          "triples": 0,
          "hr": 0,
          "bb": 0,
          "hbp": 0,
          "sf": 0,
          "sh": 0
        },
        {
          "name": "Brown, Autumn",
          "ab": 3,
          "h": 2,
          "doubles": 1,
          "triples": 0,
          "hr": 0,
          "bb": 0,
          "hbp": 0,
          "sf": 0,
          "sh": 0
        },
        {
          "name": "Moniz, Hayley",
          "ab": 3,
          "h": 1,
          "doubles": 0,
          "triples": 0,
          "hr": 0,
          "bb": 0,
          "hbp": 0,
          "sf": 0,
          "sh": 0
        },
        {
          "name": "O'Shea, Jill",
          "ab": 3,
          "h": 0,
          "doubles": 0,
          "triples": 0,
          "hr": 0,
          "bb": 0,
          "hbp": 0,
          "sf": 0,
          "sh": 0
        },
        {
          "name": "Griffin, Julianne",
          "ab": 3,
          "h": 0,
          "doubles": 0,
          "triples": 0,
          "hr": 0,
          "bb": 0,
          "hbp": 0,
          "sf": 0,
          "sh": 0
        },
        {
          "name": "McMorrow, Haley",
          "ab": 0,
          "h": 0,
          "doubles": 0,
          "triples": 0,
          "hr": 0,
          "bb": 0,
          "hbp": 0,
          "sf": 0,
          "sh": 0
        }
      ]
    },
    {
      "date": "5/3/2019",
      "opponent": "Emerson",
      "url": "https://wellesleyblue.com/sports/softball/stats/2019/emerson/boxscore/997",
      "playerStats": [
        {
          "name": "Smith, Kendall",
          "ab": 3,
          "h": 0,
          "doubles": 0,
          "triples": 0,
          "hr": 0,
          "bb": 0,
          "hbp": 0,
          "sf": 0,
          "sh": 0
        },
        {
          "name": "Hana, Alyssa",
          "ab": 4,
          "h": 0,
          "doubles": 0,
          "triples": 0,
          "hr": 0,
          "bb": 0,
          "hbp": 0,
          "sf": 0,
          "sh": 0
        },
        {
          "name": "Hensch, Marisa",
          "ab": 3,
          "h": 1,
          "doubles": 0,
          "triples": 0,
          "hr": 0,
          "bb": 0,
          "hbp": 0,
          "sf": 0,
          "sh": 0
        },
        {
          "name": "Brittingham, Gen",
          "ab": 3,
          "h": 1,
          "doubles": 0,
          "triples": 0,
          "hr": 0,
          "bb": 0,
          "hbp": 0,
          "sf": 1,
          "sh": 0
        },
        {
          "name": "Oliver, Kalei",
          "ab": 3,
          "h": 2,
          "doubles": 0,
          "triples": 0,
          "hr": 0,
          "bb": 1,
          "hbp": 0,
          "sf": 0,
          "sh": 0
        },
        {
          "name": "Brown, Autumn",
          "ab": 4,
          "h": 2,
          "doubles": 1,
          "triples": 0,
          "hr": 0,
          "bb": 0,
          "hbp": 0,
          "sf": 0,
          "sh": 0
        },
        {
          "name": "Cheskin, Lucy",
          "ab": 0,
          "h": 0,
          "doubles": 0,
          "triples": 0,
          "hr": 0,
          "bb": 0,
          "hbp": 0,
          "sf": 0,
          "sh": 0
        },
        {
          "name": "Moniz, Hayley",
          "ab": 2,
          "h": 0,
          "doubles": 0,
          "triples": 0,
          "hr": 0,
          "bb": 1,
          "hbp": 0,
          "sf": 0,
          "sh": 0
        },
        {
          "name": "O'Shea, Jill",
          "ab": 3,
          "h": 1,
          "doubles": 0,
          "triples": 0,
          "hr": 0,
          "bb": 0,
          "hbp": 0,
          "sf": 0,
          "sh": 0
        },
        {
          "name": "Chin, Holly",
          "ab": 0,
          "h": 0,
          "doubles": 0,
          "triples": 0,
          "hr": 0,
          "bb": 0,
          "hbp": 0,
          "sf": 0,
          "sh": 0
        },
        {
          "name": "Griffin, Julianne",
          "ab": 1,
          "h": 1,
          "doubles": 1,
          "triples": 0,
          "hr": 0,
          "bb": 2,
          "hbp": 0,
          "sf": 0,
          "sh": 0
        },
        {
          "name": "Gordon, Caitlin",
          "ab": 0,
          "h": 0,
          "doubles": 0,
          "triples": 0,
          "hr": 0,
          "bb": 0,
          "hbp": 0,
          "sf": 0,
          "sh": 0
        }
      ]
    },
    {
      "date": "5/3/2019",
      "opponent": "Babson",
      "url": "https://wellesleyblue.com/sports/softball/stats/2019/babson/boxscore/998",
      "playerStats": [
        {
          "name": "Smith, Kendall",
          "ab": 4,
          "h": 2,
          "doubles": 1,
          "triples": 0,
          "hr": 0,
          "bb": 1,
          "hbp": 0,
          "sf": 0,
          "sh": 0
        },
        {
          "name": "Hana, Alyssa",
          "ab": 4,
          "h": 0,
          "doubles": 0,
          "triples": 0,
          "hr": 0,
          "bb": 0,
          "hbp": 0,
          "sf": 0,
          "sh": 1
        },
        {
          "name": "Hensch, Marisa",
          "ab": 5,
          "h": 1,
          "doubles": 0,
          "triples": 0,
          "hr": 0,
          "bb": 0,
          "hbp": 0,
          "sf": 0,
          "sh": 0
        },
        {
          "name": "Brittingham, Gen",
          "ab": 5,
          "h": 4,
          "doubles": 0,
          "triples": 0,
          "hr": 1,
          "bb": 0,
          "hbp": 0,
          "sf": 0,
          "sh": 0
        },
        {
          "name": "Oliver, Kalei",
          "ab": 4,
          "h": 2,
          "doubles": 0,
          "triples": 0,
          "hr": 0,
          "bb": 0,
          "hbp": 0,
          "sf": 0,
          "sh": 1
        },
        {
          "name": "Brown, Autumn",
          "ab": 5,
          "h": 0,
          "doubles": 0,
          "triples": 0,
          "hr": 0,
          "bb": 0,
          "hbp": 0,
          "sf": 0,
          "sh": 0
        },
        {
          "name": "Moniz, Hayley",
          "ab": 4,
          "h": 1,
          "doubles": 1,
          "triples": 0,
          "hr": 0,
          "bb": 0,
          "hbp": 0,
          "sf": 0,
          "sh": 0
        },
        {
          "name": "O'Shea, Jill",
          "ab": 4,
          "h": 1,
          "doubles": 0,
          "triples": 0,
          "hr": 0,
          "bb": 0,
          "hbp": 0,
          "sf": 0,
          "sh": 0
        },
        {
          "name": "Chin, Holly",
          "ab": 0,
          "h": 0,
          "doubles": 0,
          "triples": 0,
          "hr": 0,
          "bb": 0,
          "hbp": 0,
          "sf": 0,
          "sh": 0
        },
        {
          "name": "Griffin, Julianne",
          "ab": 4,
          "h": 2,
          "doubles": 0,
          "triples": 0,
          "hr": 0,
          "bb": 0,
          "hbp": 0,
          "sf": 0,
          "sh": 0
        },
        {
          "name": "Gordon, Caitlin",
          "ab": 0,
          "h": 0,
          "doubles": 0,
          "triples": 0,
          "hr": 0,
          "bb": 0,
          "hbp": 0,
          "sf": 0,
          "sh": 0
        }
      ]
    },
    {
      "date": "5/4/2019",
      "opponent": "Wpi",
      "url": "https://wellesleyblue.com/sports/softball/stats/2019/wpi/boxscore/999",
      "playerStats": [
        {
          "name": "Smith, Kendall",
          "ab": 4,
          "h": 0,
          "doubles": 0,
          "triples": 0,
          "hr": 0,
          "bb": 0,
          "hbp": 0,
          "sf": 0,
          "sh": 0
        },
        {
          "name": "Hana, Alyssa",
          "ab": 4,
          "h": 0,
          "doubles": 0,
          "triples": 0,
          "hr": 0,
          "bb": 0,
          "hbp": 0,
          "sf": 0,
          "sh": 0
        },
        {
          "name": "Hensch, Marisa",
          "ab": 3,
          "h": 2,
          "doubles": 1,
          "triples": 0,
          "hr": 0,
          "bb": 0,
          "hbp": 0,
          "sf": 0,
          "sh": 0
        },
        {
          "name": "Brittingham, Gen",
          "ab": 3,
          "h": 1,
          "doubles": 1,
          "triples": 0,
          "hr": 0,
          "bb": 0,
          "hbp": 0,
          "sf": 0,
          "sh": 0
        },
        {
          "name": "Oliver, Kalei",
          "ab": 2,
          "h": 2,
          "doubles": 0,
          "triples": 0,
          "hr": 0,
          "bb": 1,
          "hbp": 0,
          "sf": 0,
          "sh": 0
        },
        {
          "name": "Brown, Autumn",
          "ab": 3,
          "h": 0,
          "doubles": 0,
          "triples": 0,
          "hr": 0,
          "bb": 0,
          "hbp": 0,
          "sf": 0,
          "sh": 0
        },
        {
          "name": "Moniz, Hayley",
          "ab": 3,
          "h": 0,
          "doubles": 0,
          "triples": 0,
          "hr": 0,
          "bb": 0,
          "hbp": 0,
          "sf": 0,
          "sh": 0
        },
        {
          "name": "O'Shea, Jill",
          "ab": 3,
          "h": 1,
          "doubles": 0,
          "triples": 0,
          "hr": 0,
          "bb": 0,
          "hbp": 0,
          "sf": 0,
          "sh": 0
        },
        {
          "name": "Cheskin, Lucy",
          "ab": 0,
          "h": 0,
          "doubles": 0,
          "triples": 0,
          "hr": 0,
          "bb": 0,
          "hbp": 0,
          "sf": 0,
          "sh": 0
        },
        {
          "name": "Griffin, Julianne",
          "ab": 2,
          "h": 0,
          "doubles": 0,
          "triples": 0,
          "hr": 0,
          "bb": 0,
          "hbp": 0,
          "sf": 0,
          "sh": 1
        },
        {
          "name": "Gordon, Caitlin",
          "ab": 0,
          "h": 0,
          "doubles": 0,
          "triples": 0,
          "hr": 0,
          "bb": 0,
          "hbp": 0,
          "sf": 0,
          "sh": 0
        }
      ]
    }
  ]
}
