{
  "slug": "smith",
  "domain": "gosmithbears.com",
  "scrapedAt": "2026-04-26T02:33:29.758Z",
  "year": 2026,
  "teamGames": 33,
  "players": [
    {
      "name": "Ally Knutson",
      "jerseyNumber": 6,
      "classYear": "Junior",
      "position": "Outfielder",
      "bats": null,
      "season": {
        "year": 2026,
        "name": "Knutson, Ally",
        "avg": 0.421,
        "ops": 1.053,
        "gp": 33,
        "gs": 33,
        "ab": 121,
        "r": 29,
        "h": 51,
        "doubles": 18,
        "triples": 2,
        "hr": 0,
        "rbi": 27,
        "tb": 73,
        "slg": 0.603,
        "bb": 6,
        "hbp": 1,
        "so": 9,
        "gdp": 0,
        "obp": 0.45,
        "sf": 1,
        "sh": 0,
        "sb": 6,
        "sbAtt": 7,
        "woba": 0.437,
        "pa": 129
      }
    },
    {
      "name": "Violet Peverly",
      "jerseyNumber": 20,
      "classYear": "First Year",
      "position": "Pitcher/Infielder",
      "bats": null,
      "season": {
        "year": 2026,
        "name": "Peverly, Violet",
        "avg": 0.33,
        "ops": 0.863,
        "gp": 33,
        "gs": 33,
        "ab": 103,
        "r": 19,
        "h": 34,
        "doubles": 6,
        "triples": 1,
        "hr": 2,
        "rbi": 20,
        "tb": 48,
        "slg": 0.466,
        "bb": 10,
        "hbp": 2,
        "so": 10,
        "gdp": 0,
        "obp": 0.397,
        "sf": 1,
        "sh": 2,
        "sb": 11,
        "sbAtt": 14,
        "woba": 0.359,
        "pa": 118
      }
    },
    {
      "name": "Sophie Hasegawa",
      "jerseyNumber": 21,
      "classYear": "First Year",
      "position": "Infielder",
      "bats": null,
      "season": {
        "year": 2026,
        "name": "Hasegawa, Sophie",
        "avg": 0.321,
        "ops": 0.827,
        "gp": 33,
        "gs": 33,
        "ab": 84,
        "r": 18,
        "h": 27,
        "doubles": 2,
        "triples": 1,
        "hr": 0,
        "rbi": 13,
        "tb": 31,
        "slg": 0.369,
        "bb": 18,
        "hbp": 4,
        "so": 11,
        "gdp": 0,
        "obp": 0.458,
        "sf": 1,
        "sh": 3,
        "sb": 9,
        "sbAtt": 11,
        "woba": 0.334,
        "pa": 110
      }
    },
    {
      "name": "Riley Veenstra",
      "jerseyNumber": 10,
      "classYear": "First Year",
      "position": "Catcher/Infielder",
      "bats": null,
      "season": {
        "year": 2026,
        "name": "Veenstra, Riley",
        "avg": 0.315,
        "ops": 0.786,
        "gp": 33,
        "gs": 33,
        "ab": 89,
        "r": 8,
        "h": 28,
        "doubles": 4,
        "triples": 0,
        "hr": 0,
        "rbi": 18,
        "tb": 32,
        "slg": 0.36,
        "bb": 17,
        "hbp": 1,
        "so": 10,
        "gdp": 2,
        "obp": 0.426,
        "sf": 1,
        "sh": 1,
        "sb": 0,
        "sbAtt": 0,
        "woba": 0.325,
        "pa": 109
      }
    },
    {
      "name": "Gabbie Chinnis",
      "jerseyNumber": 5,
      "classYear": "First Year",
      "position": "Infielder",
      "bats": null,
      "season": {
        "year": 2026,
        "name": "Chinnis, Gabbie",
        "avg": 0.33,
        "ops": 0.772,
        "gp": 32,
        "gs": 30,
        "ab": 100,
        "r": 27,
        "h": 33,
        "doubles": 1,
        "triples": 1,
        "hr": 0,
        "rbi": 10,
        "tb": 36,
        "slg": 0.36,
        "bb": 13,
        "hbp": 1,
        "so": 11,
        "gdp": 0,
        "obp": 0.412,
        "sf": 0,
        "sh": 3,
        "sb": 21,
        "sbAtt": 21,
        "woba": 0.323,
        "pa": 117
      }
    },
    {
      "name": "Bailey Gray",
      "jerseyNumber": 23,
      "classYear": "Junior",
      "position": "Pitcher/Outfielder",
      "bats": null,
      "season": {
        "year": 2026,
        "name": "Gray, Bailey",
        "avg": 0.347,
        "ops": 0.755,
        "gp": 32,
        "gs": 31,
        "ab": 98,
        "r": 18,
        "h": 34,
        "doubles": 6,
        "triples": 0,
        "hr": 0,
        "rbi": 17,
        "tb": 40,
        "slg": 0.408,
        "bb": 1,
        "hbp": 0,
        "so": 4,
        "gdp": 0,
        "obp": 0.347,
        "sf": 2,
        "sh": 2,
        "sb": 3,
        "sbAtt": 4,
        "woba": 0.319,
        "pa": 103
      }
    },
    {
      "name": "Taz Tamai",
      "jerseyNumber": 2,
      "classYear": "Junior",
      "position": "Infielder",
      "bats": null,
      "season": {
        "year": 2026,
        "name": "Tamai, Taz",
        "avg": 0.305,
        "ops": 0.78,
        "gp": 33,
        "gs": 33,
        "ab": 82,
        "r": 15,
        "h": 25,
        "doubles": 5,
        "triples": 0,
        "hr": 0,
        "rbi": 15,
        "tb": 30,
        "slg": 0.366,
        "bb": 14,
        "hbp": 2,
        "so": 16,
        "gdp": 0,
        "obp": 0.414,
        "sf": 1,
        "sh": 4,
        "sb": 3,
        "sbAtt": 3,
        "woba": 0.311,
        "pa": 103
      }
    },
    {
      "name": "Elinor Washington",
      "jerseyNumber": 7,
      "classYear": "Senior",
      "position": "Outfielder",
      "bats": null,
      "season": {
        "year": 2026,
        "name": "Washington, Elinor",
        "avg": 0.277,
        "ops": 0.701,
        "gp": 31,
        "gs": 29,
        "ab": 83,
        "r": 14,
        "h": 23,
        "doubles": 9,
        "triples": 0,
        "hr": 0,
        "rbi": 16,
        "tb": 32,
        "slg": 0.386,
        "bb": 4,
        "hbp": 1,
        "so": 16,
        "gdp": 0,
        "obp": 0.315,
        "sf": 1,
        "sh": 3,
        "sb": 2,
        "sbAtt": 3,
        "woba": 0.282,
        "pa": 92
      }
    },
    {
      "name": "Lindsay Bennett",
      "jerseyNumber": 8,
      "classYear": "Sophomore",
      "position": "Pitcher/Utility",
      "bats": null,
      "season": {
        "year": 2026,
        "name": "Bennett, Lindsay",
        "avg": 0,
        "ops": 0.5,
        "gp": 11,
        "gs": 0,
        "ab": 1,
        "r": 0,
        "h": 0,
        "doubles": 0,
        "triples": 0,
        "hr": 0,
        "rbi": 1,
        "tb": 0,
        "slg": 0,
        "bb": 0,
        "hbp": 1,
        "so": 1,
        "gdp": 0,
        "obp": 0.5,
        "sf": 0,
        "sh": 0,
        "sb": 0,
        "sbAtt": 0,
        "woba": 0.25,
        "pa": 2
      }
    },
    {
      "name": "Lily Hackett",
      "jerseyNumber": 1,
      "classYear": "Sophomore",
      "position": "Infielder",
      "bats": null,
      "season": {
        "year": 2026,
        "name": "Hackett, Lily",
        "avg": 0.243,
        "ops": 0.575,
        "gp": 33,
        "gs": 33,
        "ab": 70,
        "r": 6,
        "h": 17,
        "doubles": 3,
        "triples": 0,
        "hr": 0,
        "rbi": 10,
        "tb": 20,
        "slg": 0.286,
        "bb": 5,
        "hbp": 0,
        "so": 13,
        "gdp": 1,
        "obp": 0.289,
        "sf": 1,
        "sh": 3,
        "sb": 2,
        "sbAtt": 3,
        "woba": 0.237,
        "pa": 79
      }
    },
    {
      "name": "Lucy Allen",
      "jerseyNumber": 12,
      "classYear": "Junior",
      "position": "Catcher",
      "bats": null,
      "season": {
        "year": 2026,
        "name": "Allen, Lucy",
        "avg": 0.176,
        "ops": 0.439,
        "gp": 17,
        "gs": 15,
        "ab": 17,
        "r": 5,
        "h": 3,
        "doubles": 0,
        "triples": 0,
        "hr": 0,
        "rbi": 4,
        "tb": 3,
        "slg": 0.176,
        "bb": 2,
        "hbp": 0,
        "so": 2,
        "gdp": 0,
        "obp": 0.263,
        "sf": 0,
        "sh": 1,
        "sb": 0,
        "sbAtt": 1,
        "woba": 0.185,
        "pa": 20
      }
    },
    {
      "name": "Malaya Sumii",
      "jerseyNumber": 24,
      "classYear": "First Year",
      "position": "Infielder",
      "bats": null,
      "season": {
        "year": 2026,
        "name": "Sumii, Malaya",
        "avg": 0.111,
        "ops": 0.311,
        "gp": 9,
        "gs": 0,
        "ab": 9,
        "r": 1,
        "h": 1,
        "doubles": 0,
        "triples": 0,
        "hr": 0,
        "rbi": 1,
        "tb": 1,
        "slg": 0.111,
        "bb": 1,
        "hbp": 0,
        "so": 2,
        "gdp": 0,
        "obp": 0.2,
        "sf": 0,
        "sh": 0,
        "sb": 0,
        "sbAtt": 0,
        "woba": 0.14,
        "pa": 10
      }
    },
    {
      "name": "Maya  Patankar",
      "jerseyNumber": 18,
      "classYear": "First Year",
      "position": "Catcher/Infielder",
      "bats": null,
      "season": {
        "year": 2026,
        "name": "Patankar, Maya",
        "avg": 0,
        "ops": 0.25,
        "gp": 5,
        "gs": 0,
        "ab": 3,
        "r": 1,
        "h": 0,
        "doubles": 0,
        "triples": 0,
        "hr": 0,
        "rbi": 0,
        "tb": 0,
        "slg": 0,
        "bb": 1,
        "hbp": 0,
        "so": 2,
        "gdp": 0,
        "obp": 0.25,
        "sf": 0,
        "sh": 0,
        "sb": 0,
        "sbAtt": 0,
        "woba": 0.125,
        "pa": 4
      }
    },
    {
      "name": "Alana Robinson",
      "jerseyNumber": 25,
      "classYear": "First Year",
      "position": "Pitcher/Infielder",
      "bats": null,
      "season": {
        "year": 2026,
        "name": "Robinson, Alana",
        "avg": 0.05,
        "ops": 0.21,
        "gp": 16,
        "gs": 9,
        "ab": 20,
        "r": 0,
        "h": 1,
        "doubles": 0,
        "triples": 0,
        "hr": 0,
        "rbi": 2,
        "tb": 1,
        "slg": 0.05,
        "bb": 2,
        "hbp": 1,
        "so": 5,
        "gdp": 0,
        "obp": 0.16,
        "sf": 2,
        "sh": 0,
        "sb": 0,
        "sbAtt": 0,
        "woba": 0.096,
        "pa": 25
      }
    },
    {
      "name": "Ava Lansbury",
      "jerseyNumber": 13,
      "classYear": "Junior",
      "position": "Catcher",
      "bats": null,
      "season": {
        "year": 2026,
        "name": "Lansbury, Ava",
        "avg": 0,
        "ops": 0.143,
        "gp": 16,
        "gs": 15,
        "ab": 6,
        "r": 1,
        "h": 0,
        "doubles": 0,
        "triples": 0,
        "hr": 0,
        "rbi": 0,
        "tb": 0,
        "slg": 0,
        "bb": 1,
        "hbp": 0,
        "so": 3,
        "gdp": 0,
        "obp": 0.143,
        "sf": 0,
        "sh": 0,
        "sb": 0,
        "sbAtt": 0,
        "woba": 0.071,
        "pa": 7
      }
    },
    {
      "name": "Anna Gray",
      "jerseyNumber": 3,
      "classYear": "First Year",
      "position": "Outfielder",
      "bats": null,
      "season": {
        "year": 2026,
        "name": "Gray, Anna",
        "avg": 0,
        "ops": 0,
        "gp": 23,
        "gs": 0,
        "ab": 2,
        "r": 10,
        "h": 0,
        "doubles": 0,
        "triples": 0,
        "hr": 0,
        "rbi": 0,
        "tb": 0,
        "slg": 0,
        "bb": 0,
        "hbp": 0,
        "so": 2,
        "gdp": 0,
        "obp": 0,
        "sf": 0,
        "sh": 0,
        "sb": 1,
        "sbAtt": 1,
        "woba": 0,
        "pa": 2
      }
    }
  ]
}