{
  "slug": "brockport",
  "domain": "gobrockport.com",
  "scrapedAt": "2026-05-07T02:41:25.235Z",
  "year": 2026,
  "hitting": {
    "players": [
      {
        "name": "Dailey, Caitlyn",
        "jerseyNumber": 5,
        "avg": 0.327,
        "ops": 0.801,
        "gp": 34,
        "gs": 34,
        "ab": 107,
        "r": 10,
        "h": 35,
        "doubles": 7,
        "triples": 1,
        "hr": 1,
        "rbi": 27,
        "tb": 47,
        "slg": 0.439,
        "bb": 4,
        "hbp": 3,
        "so": 15,
        "gdp": 1,
        "obp": 0.362,
        "sf": 2,
        "sh": 4,
        "sb": 0,
        "sbAtt": 1
      },
      {
        "name": "Hill, Julia",
        "jerseyNumber": 3,
        "avg": 0.313,
        "ops": 0.865,
        "gp": 34,
        "gs": 30,
        "ab": 99,
        "r": 29,
        "h": 31,
        "doubles": 7,
        "triples": 1,
        "hr": 4,
        "rbi": 26,
        "tb": 52,
        "slg": 0.525,
        "bb": 5,
        "hbp": 0,
        "so": 11,
        "gdp": 0,
        "obp": 0.34,
        "sf": 2,
        "sh": 3,
        "sb": 6,
        "sbAtt": 6
      },
      {
        "name": "Ayers, Saylor",
        "jerseyNumber": 18,
        "avg": 0.309,
        "ops": 0.836,
        "gp": 32,
        "gs": 28,
        "ab": 55,
        "r": 10,
        "h": 17,
        "doubles": 4,
        "triples": 0,
        "hr": 1,
        "rbi": 4,
        "tb": 24,
        "slg": 0.436,
        "bb": 9,
        "hbp": 0,
        "so": 20,
        "gdp": 0,
        "obp": 0.4,
        "sf": 1,
        "sh": 4,
        "sb": 1,
        "sbAtt": 1
      },
      {
        "name": "DeValder, Liana",
        "jerseyNumber": 15,
        "avg": 0.305,
        "ops": 1.029,
        "gp": 33,
        "gs": 26,
        "ab": 82,
        "r": 15,
        "h": 25,
        "doubles": 11,
        "triples": 2,
        "hr": 3,
        "rbi": 25,
        "tb": 49,
        "slg": 0.598,
        "bb": 19,
        "hbp": 0,
        "so": 13,
        "gdp": 0,
        "obp": 0.431,
        "sf": 1,
        "sh": 0,
        "sb": 1,
        "sbAtt": 2
      },
      {
        "name": "Wentland, Paige",
        "jerseyNumber": 20,
        "avg": 0.277,
        "ops": 0.661,
        "gp": 32,
        "gs": 32,
        "ab": 83,
        "r": 8,
        "h": 23,
        "doubles": 3,
        "triples": 0,
        "hr": 0,
        "rbi": 11,
        "tb": 26,
        "slg": 0.313,
        "bb": 8,
        "hbp": 1,
        "so": 15,
        "gdp": 0,
        "obp": 0.348,
        "sf": 0,
        "sh": 1,
        "sb": 0,
        "sbAtt": 0
      },
      {
        "name": "Dougherty , Erin",
        "jerseyNumber": 2,
        "avg": 0.222,
        "ops": 0.566,
        "gp": 35,
        "gs": 35,
        "ab": 81,
        "r": 20,
        "h": 18,
        "doubles": 0,
        "triples": 0,
        "hr": 0,
        "rbi": 3,
        "tb": 18,
        "slg": 0.222,
        "bb": 15,
        "hbp": 0,
        "so": 30,
        "gdp": 0,
        "obp": 0.344,
        "sf": 0,
        "sh": 4,
        "sb": 11,
        "sbAtt": 12
      },
      {
        "name": "Faas, Natalie",
        "jerseyNumber": 17,
        "avg": 0.435,
        "ops": 0.973,
        "gp": 21,
        "gs": 21,
        "ab": 62,
        "r": 16,
        "h": 27,
        "doubles": 1,
        "triples": 0,
        "hr": 0,
        "rbi": 6,
        "tb": 28,
        "slg": 0.452,
        "bb": 10,
        "hbp": 1,
        "so": 8,
        "gdp": 0,
        "obp": 0.521,
        "sf": 0,
        "sh": 0,
        "sb": 5,
        "sbAtt": 7
      },
      {
        "name": "Sabins, Aurora",
        "jerseyNumber": 22,
        "avg": 0.286,
        "ops": 0.637,
        "gp": 21,
        "gs": 1,
        "ab": 21,
        "r": 2,
        "h": 6,
        "doubles": 1,
        "triples": 0,
        "hr": 0,
        "rbi": 7,
        "tb": 7,
        "slg": 0.333,
        "bb": 1,
        "hbp": 0,
        "so": 4,
        "gdp": 0,
        "obp": 0.304,
        "sf": 1,
        "sh": 0,
        "sb": 0,
        "sbAtt": 0
      },
      {
        "name": "Davis, Colleen",
        "jerseyNumber": 16,
        "avg": 0.276,
        "ops": 0.754,
        "gp": 25,
        "gs": 19,
        "ab": 58,
        "r": 6,
        "h": 16,
        "doubles": 5,
        "triples": 2,
        "hr": 0,
        "rbi": 9,
        "tb": 25,
        "slg": 0.431,
        "bb": 1,
        "hbp": 3,
        "so": 7,
        "gdp": 1,
        "obp": 0.323,
        "sf": 0,
        "sh": 0,
        "sb": 2,
        "sbAtt": 2
      },
      {
        "name": "Ennis, Aubrey",
        "jerseyNumber": 25,
        "avg": 0.245,
        "ops": 0.828,
        "gp": 25,
        "gs": 18,
        "ab": 53,
        "r": 4,
        "h": 13,
        "doubles": 7,
        "triples": 0,
        "hr": 1,
        "rbi": 6,
        "tb": 23,
        "slg": 0.434,
        "bb": 10,
        "hbp": 3,
        "so": 8,
        "gdp": 1,
        "obp": 0.394,
        "sf": 0,
        "sh": 1,
        "sb": 0,
        "sbAtt": 0
      },
      {
        "name": "Brannigan, Maeve",
        "jerseyNumber": 23,
        "avg": 0.231,
        "ops": 0.541,
        "gp": 13,
        "gs": 7,
        "ab": 26,
        "r": 2,
        "h": 6,
        "doubles": 0,
        "triples": 0,
        "hr": 0,
        "rbi": 3,
        "tb": 6,
        "slg": 0.231,
        "bb": 3,
        "hbp": 0,
        "so": 4,
        "gdp": 0,
        "obp": 0.31,
        "sf": 0,
        "sh": 1,
        "sb": 0,
        "sbAtt": 0
      },
      {
        "name": "Harrington, Emily",
        "jerseyNumber": 10,
        "avg": 0.206,
        "ops": 0.657,
        "gp": 18,
        "gs": 14,
        "ab": 34,
        "r": 3,
        "h": 7,
        "doubles": 1,
        "triples": 0,
        "hr": 1,
        "rbi": 4,
        "tb": 11,
        "slg": 0.324,
        "bb": 7,
        "hbp": 0,
        "so": 10,
        "gdp": 0,
        "obp": 0.333,
        "sf": 1,
        "sh": 1,
        "sb": 0,
        "sbAtt": 0
      },
      {
        "name": "Moya, Isabella",
        "jerseyNumber": 9,
        "avg": 0.179,
        "ops": 0.508,
        "gp": 27,
        "gs": 19,
        "ab": 28,
        "r": 13,
        "h": 5,
        "doubles": 2,
        "triples": 0,
        "hr": 0,
        "rbi": 5,
        "tb": 7,
        "slg": 0.25,
        "bb": 2,
        "hbp": 1,
        "so": 11,
        "gdp": 0,
        "obp": 0.258,
        "sf": 0,
        "sh": 2,
        "sb": 6,
        "sbAtt": 7
      },
      {
        "name": "Cotty, Teresa",
        "jerseyNumber": 27,
        "avg": 0.172,
        "ops": 0.422,
        "gp": 15,
        "gs": 8,
        "ab": 29,
        "r": 2,
        "h": 5,
        "doubles": 0,
        "triples": 0,
        "hr": 0,
        "rbi": 2,
        "tb": 5,
        "slg": 0.172,
        "bb": 2,
        "hbp": 1,
        "so": 6,
        "gdp": 0,
        "obp": 0.25,
        "sf": 0,
        "sh": 1,
        "sb": 0,
        "sbAtt": 0
      },
      {
        "name": "Lovgren, Lila",
        "jerseyNumber": 21,
        "avg": 0.167,
        "ops": 0.579,
        "gp": 24,
        "gs": 9,
        "ab": 12,
        "r": 10,
        "h": 2,
        "doubles": 0,
        "triples": 0,
        "hr": 0,
        "rbi": 1,
        "tb": 2,
        "slg": 0.167,
        "bb": 5,
        "hbp": 0,
        "so": 3,
        "gdp": 0,
        "obp": 0.412,
        "sf": 0,
        "sh": 0,
        "sb": 5,
        "sbAtt": 5
      },
      {
        "name": "Myers, Reagan",
        "jerseyNumber": 8,
        "avg": 0.16,
        "ops": 0.394,
        "gp": 23,
        "gs": 21,
        "ab": 50,
        "r": 5,
        "h": 8,
        "doubles": 1,
        "triples": 0,
        "hr": 0,
        "rbi": 8,
        "tb": 9,
        "slg": 0.18,
        "bb": 4,
        "hbp": 0,
        "so": 20,
        "gdp": 0,
        "obp": 0.214,
        "sf": 2,
        "sh": 2,
        "sb": 0,
        "sbAtt": 0
      },
      {
        "name": "Hart, Makenna",
        "jerseyNumber": 7,
        "avg": 0.1,
        "ops": 0.2,
        "gp": 12,
        "gs": 9,
        "ab": 10,
        "r": 1,
        "h": 1,
        "doubles": 0,
        "triples": 0,
        "hr": 0,
        "rbi": 0,
        "tb": 1,
        "slg": 0.1,
        "bb": 0,
        "hbp": 0,
        "so": 5,
        "gdp": 0,
        "obp": 0.1,
        "sf": 0,
        "sh": 0,
        "sb": 0,
        "sbAtt": 0
      },
      {
        "name": "Parente, Isabella",
        "jerseyNumber": 14,
        "avg": 0,
        "ops": 0.222,
        "gp": 6,
        "gs": 2,
        "ab": 7,
        "r": 0,
        "h": 0,
        "doubles": 0,
        "triples": 0,
        "hr": 0,
        "rbi": 0,
        "tb": 0,
        "slg": 0,
        "bb": 1,
        "hbp": 1,
        "so": 3,
        "gdp": 0,
        "obp": 0.222,
        "sf": 0,
        "sh": 0,
        "sb": 0,
        "sbAtt": 0
      },
      {
        "name": "Alguire, Hadley",
        "jerseyNumber": 11,
        "avg": 0,
        "ops": 0.25,
        "gp": 7,
        "gs": 3,
        "ab": 3,
        "r": 0,
        "h": 0,
        "doubles": 0,
        "triples": 0,
        "hr": 0,
        "rbi": 0,
        "tb": 0,
        "slg": 0,
        "bb": 1,
        "hbp": 0,
        "so": 0,
        "gdp": 0,
        "obp": 0.25,
        "sf": 0,
        "sh": 0,
        "sb": 0,
        "sbAtt": 0
      },
      {
        "name": "Olivo, Ciara",
        "jerseyNumber": 19,
        "avg": 0,
        "ops": 0.5,
        "gp": 23,
        "gs": 13,
        "ab": 2,
        "r": 6,
        "h": 0,
        "doubles": 0,
        "triples": 0,
        "hr": 0,
        "rbi": 0,
        "tb": 0,
        "slg": 0,
        "bb": 2,
        "hbp": 0,
        "so": 1,
        "gdp": 0,
        "obp": 0.5,
        "sf": 0,
        "sh": 0,
        "sb": 2,
        "sbAtt": 3
      },
      {
        "name": "Ernewein, Drew",
        "jerseyNumber": 12,
        "avg": 0,
        "ops": 0,
        "gp": 1,
        "gs": 0,
        "ab": 1,
        "r": 0,
        "h": 0,
        "doubles": 0,
        "triples": 0,
        "hr": 0,
        "rbi": 0,
        "tb": 0,
        "slg": 0,
        "bb": 0,
        "hbp": 0,
        "so": 0,
        "gdp": 0,
        "obp": 0,
        "sf": 0,
        "sh": 0,
        "sb": 0,
        "sbAtt": 0
      }
    ],
    "totals": {
      "avg": 0.271,
      "ops": 0.732,
      "gp": 35,
      "gs": 35,
      "ab": 903,
      "r": 162,
      "h": 245,
      "doubles": 50,
      "triples": 6,
      "hr": 11,
      "rbi": 147,
      "tb": 340,
      "slg": 0.377,
      "bb": 109,
      "hbp": 14,
      "so": 194,
      "gdp": 3,
      "obp": 0.355,
      "sf": 10,
      "sh": 24,
      "sb": 39,
      "sbAtt": 46
    },
    "opponents": {
      "avg": 0.29,
      "ops": 0.739,
      "gp": 35,
      "gs": 35,
      "ab": 956,
      "r": 177,
      "h": 277,
      "doubles": 39,
      "triples": 4,
      "hr": 15,
      "rbi": 148,
      "tb": 369,
      "slg": 0.386,
      "bb": 82,
      "hbp": 14,
      "so": 174,
      "gdp": 0,
      "obp": 0.353,
      "sf": 5,
      "sh": 23,
      "sb": 60,
      "sbAtt": 68
    }
  },
  "pitching": {
    "players": [
      {
        "name": "DeValder, Liana",
        "jerseyNumber": 15,
        "era": 2.29,
        "whip": 1.09,
        "w": 11,
        "l": 5,
        "app": 20,
        "gs": 13,
        "cg": 12,
        "sho": 4,
        "sv": 1,
        "ip": 100.2,
        "h": 92,
        "r": 43,
        "er": 33,
        "bb": 18,
        "so": 111,
        "doubles": 18,
        "triples": 2,
        "hr": 7,
        "ab": 389,
        "bAvg": 0.237,
        "wp": 2,
        "hbp": 3,
        "bk": 0,
        "sfa": 1,
        "sha": 11
      },
      {
        "name": "Davis, Colleen",
        "jerseyNumber": 16,
        "era": 4.7,
        "whip": 1.97,
        "w": 5,
        "l": 5,
        "app": 16,
        "gs": 10,
        "cg": 6,
        "sho": 1,
        "sv": 1,
        "ip": 67,
        "h": 93,
        "r": 74,
        "er": 45,
        "bb": 39,
        "so": 37,
        "doubles": 10,
        "triples": 2,
        "hr": 3,
        "ab": 301,
        "bAvg": 0.309,
        "wp": 11,
        "hbp": 8,
        "bk": 0,
        "sfa": 3,
        "sha": 6
      },
      {
        "name": "Hart, Makenna",
        "jerseyNumber": 7,
        "era": 4.72,
        "whip": 1.78,
        "w": 2,
        "l": 5,
        "app": 12,
        "gs": 9,
        "cg": 3,
        "sho": 0,
        "sv": 0,
        "ip": 46,
        "h": 63,
        "r": 42,
        "er": 31,
        "bb": 19,
        "so": 24,
        "doubles": 7,
        "triples": 0,
        "hr": 3,
        "ab": 199,
        "bAvg": 0.317,
        "wp": 3,
        "hbp": 2,
        "bk": 0,
        "sfa": 1,
        "sha": 6
      },
      {
        "name": "Alguire, Hadley",
        "jerseyNumber": 11,
        "era": 9.08,
        "whip": 2.84,
        "w": 0,
        "l": 2,
        "app": 7,
        "gs": 3,
        "cg": 0,
        "sho": 0,
        "sv": 0,
        "ip": 12.1,
        "h": 29,
        "r": 18,
        "er": 16,
        "bb": 6,
        "so": 2,
        "doubles": 4,
        "triples": 0,
        "hr": 2,
        "ab": 67,
        "bAvg": 0.433,
        "wp": 2,
        "hbp": 1,
        "bk": 0,
        "sfa": 0,
        "sha": 0
      }
    ],
    "totals": {
      "era": 3.87,
      "whip": 1.59,
      "w": 18,
      "l": 17,
      "app": 55,
      "gs": 35,
      "cg": 21,
      "sho": 0,
      "sv": 2,
      "ip": 226,
      "h": 277,
      "r": 177,
      "er": 125,
      "bb": 82,
      "so": 5174,
      "doubles": 39,
      "triples": 4,
      "hr": 15,
      "ab": 956,
      "bAvg": 0.29,
      "wp": 18,
      "hbp": 14,
      "bk": 0,
      "sfa": 5,
      "sha": 23
    },
    "opponents": {
      "era": 3.46,
      "whip": 1.57,
      "w": 17,
      "l": 18,
      "app": 62,
      "gs": 35,
      "cg": 15,
      "sho": 0,
      "sv": 1,
      "ip": 226.1,
      "h": 245,
      "r": 162,
      "er": 112,
      "bb": 109,
      "so": 4194,
      "doubles": 50,
      "triples": 6,
      "hr": 11,
      "ab": 903,
      "bAvg": 0.271,
      "wp": 18,
      "hbp": 14,
      "bk": 0,
      "sfa": 10,
      "sha": 24
    }
  },
  "fielding": {
    "players": [
      {
        "name": "Harrington, Emily",
        "jerseyNumber": 10,
        "tc": 89,
        "po": 84,
        "a": 5,
        "e": 0,
        "fldPct": 1,
        "dp": 0,
        "sba": 30,
        "csb": 2,
        "pb": 7,
        "ci": 0
      },
      {
        "name": "Olivo, Ciara",
        "jerseyNumber": 19,
        "tc": 17,
        "po": 15,
        "a": 2,
        "e": 0,
        "fldPct": 1,
        "dp": 0,
        "sba": 0,
        "csb": 0,
        "pb": 0,
        "ci": 0
      },
      {
        "name": "Lovgren, Lila",
        "jerseyNumber": 21,
        "tc": 9,
        "po": 8,
        "a": 1,
        "e": 0,
        "fldPct": 1,
        "dp": 0,
        "sba": 0,
        "csb": 0,
        "pb": 0,
        "ci": 0
      },
      {
        "name": "Brannigan, Maeve",
        "jerseyNumber": 23,
        "tc": 9,
        "po": 8,
        "a": 1,
        "e": 0,
        "fldPct": 1,
        "dp": 0,
        "sba": 0,
        "csb": 0,
        "pb": 0,
        "ci": 0
      },
      {
        "name": "Parente, Isabella",
        "jerseyNumber": 14,
        "tc": 2,
        "po": 2,
        "a": 0,
        "e": 0,
        "fldPct": 1,
        "dp": 0,
        "sba": 0,
        "csb": 0,
        "pb": 0,
        "ci": 0
      },
      {
        "name": "Alguire, Hadley",
        "jerseyNumber": 11,
        "tc": 1,
        "po": 0,
        "a": 1,
        "e": 0,
        "fldPct": 1,
        "dp": 0,
        "sba": 8,
        "csb": 1,
        "pb": 0,
        "ci": 0
      },
      {
        "name": "Myers, Reagan",
        "jerseyNumber": 8,
        "tc": 117,
        "po": 107,
        "a": 8,
        "e": 2,
        "fldPct": 0.983,
        "dp": 0,
        "sba": 30,
        "csb": 5,
        "pb": 4,
        "ci": 0
      },
      {
        "name": "Wentland, Paige",
        "jerseyNumber": 20,
        "tc": 174,
        "po": 165,
        "a": 5,
        "e": 4,
        "fldPct": 0.977,
        "dp": 2,
        "sba": 0,
        "csb": 0,
        "pb": 0,
        "ci": 0
      },
      {
        "name": "Ennis, Aubrey",
        "jerseyNumber": 25,
        "tc": 44,
        "po": 31,
        "a": 12,
        "e": 1,
        "fldPct": 0.977,
        "dp": 0,
        "sba": 0,
        "csb": 0,
        "pb": 0,
        "ci": 0
      },
      {
        "name": "Moya, Isabella",
        "jerseyNumber": 9,
        "tc": 42,
        "po": 41,
        "a": 0,
        "e": 1,
        "fldPct": 0.976,
        "dp": 0,
        "sba": 0,
        "csb": 0,
        "pb": 0,
        "ci": 0
      },
      {
        "name": "DeValder, Liana",
        "jerseyNumber": 15,
        "tc": 28,
        "po": 17,
        "a": 10,
        "e": 1,
        "fldPct": 0.964,
        "dp": 0,
        "sba": 15,
        "csb": 4,
        "pb": 0,
        "ci": 0
      },
      {
        "name": "Faas, Natalie",
        "jerseyNumber": 17,
        "tc": 30,
        "po": 27,
        "a": 1,
        "e": 2,
        "fldPct": 0.933,
        "dp": 0,
        "sba": 0,
        "csb": 0,
        "pb": 0,
        "ci": 0
      },
      {
        "name": "Dailey, Caitlyn",
        "jerseyNumber": 5,
        "tc": 129,
        "po": 51,
        "a": 67,
        "e": 11,
        "fldPct": 0.915,
        "dp": 3,
        "sba": 0,
        "csb": 0,
        "pb": 0,
        "ci": 0
      },
      {
        "name": "Ayers, Saylor",
        "jerseyNumber": 6,
        "tc": 33,
        "po": 30,
        "a": 0,
        "e": 3,
        "fldPct": 0.909,
        "dp": 0,
        "sba": 0,
        "csb": 0,
        "pb": 0,
        "ci": 0
      },
      {
        "name": "Davis, Colleen",
        "jerseyNumber": 16,
        "tc": 30,
        "po": 1,
        "a": 26,
        "e": 3,
        "fldPct": 0.9,
        "dp": 0,
        "sba": 19,
        "csb": 3,
        "pb": 0,
        "ci": 0
      },
      {
        "name": "Hart, Makenna",
        "jerseyNumber": 7,
        "tc": 10,
        "po": 0,
        "a": 9,
        "e": 1,
        "fldPct": 0.9,
        "dp": 1,
        "sba": 18,
        "csb": 0,
        "pb": 0,
        "ci": 0
      },
      {
        "name": "Hill, Julia",
        "jerseyNumber": 3,
        "tc": 87,
        "po": 50,
        "a": 28,
        "e": 9,
        "fldPct": 0.897,
        "dp": 1,
        "sba": 0,
        "csb": 0,
        "pb": 0,
        "ci": 0
      },
      {
        "name": "Dougherty , Erin",
        "jerseyNumber": 2,
        "tc": 106,
        "po": 40,
        "a": 49,
        "e": 17,
        "fldPct": 0.84,
        "dp": 0,
        "sba": 0,
        "csb": 0,
        "pb": 0,
        "ci": 0
      },
      {
        "name": "Ernewein, Drew",
        "jerseyNumber": 12,
        "tc": 0,
        "po": 0,
        "a": 0,
        "e": 0,
        "fldPct": 0,
        "dp": 0,
        "sba": 0,
        "csb": 0,
        "pb": 0,
        "ci": 0
      },
      {
        "name": "Sabins, Aurora",
        "jerseyNumber": 22,
        "tc": 0,
        "po": 0,
        "a": 0,
        "e": 0,
        "fldPct": 0,
        "dp": 0,
        "sba": 0,
        "csb": 0,
        "pb": 0,
        "ci": 0
      },
      {
        "name": "Cotty, Teresa",
        "jerseyNumber": 27,
        "tc": 0,
        "po": 0,
        "a": 0,
        "e": 0,
        "fldPct": 0,
        "dp": 0,
        "sba": 0,
        "csb": 0,
        "pb": 0,
        "ci": 0
      }
    ],
    "totals": {
      "tc": 957,
      "po": 677,
      "a": 225,
      "e": 55,
      "fldPct": 0.943,
      "dp": 4,
      "sba": 120,
      "csb": 15,
      "pb": 11,
      "ci": 0
    },
    "opponents": {
      "tc": 973,
      "po": 679,
      "a": 246,
      "e": 48,
      "fldPct": 0.951,
      "dp": 5,
      "sba": 78,
      "csb": 14,
      "pb": 15,
      "ci": 0
    }
  }
}